Workbook

Sheet Instructions
A1: AI-Powered Cash Flow Forecasting Template
A2: A dynamic rolling 13-week cash flow forecasting model — live data connection guides, scenario inputs, and anomaly detection.
A4: How This Workbook Is Organised
A5: Tab | B5: Purpose
A6: Scenario Inputs | B6: Set your Best / Base / Worst case assumptions here first — starting balance, growth, collection rates, cost multipliers.
A7: 13-Week Cash Flow | B7: The rolling forecast itself — select a scenario from the dropdown and it recalculates automatically.
A8: Anomaly Detection | B8: Flags any week projected to fall below your minimum cash threshold, plus large week-over-week swings.
A9: Live Data Connection Guide | B9: How to connect this workbook to your bank/accounting data instead of retyping figures manually.
A10: AI Commentary Prompts | B10: Ready-to-use prompts for generating narrative commentary with Copilot or another AI assistant.
A12: Colour Legend
A13: Blue text | B13: An input cell you should fill in or edit for your own business.
A14: Black text | B14: A formula — do not overtype, or the roll-forward logic will break.
A15: Green text | B15: A link pulling data from another tab — edit the source, not this cell.
A16: Yellow fill | B16: A key input or assumption cell, highlighted for visibility.
A18: Getting Started
A19: 1. | B19: Go to Scenario Inputs and enter your actual starting cash balance and assumptions for each scenario.
A20: 2. | B20: Go to 13-Week Cash Flow and select which scenario to view using the dropdown near the top.
A21: 3. | B21: Replace the sample receipt/payment line items with your own recurring items.
A22: 4. | B22: Review Anomaly Detection each week to catch any weeks projected to breach your minimum cash threshold.
A23: 5. | B23: Use AI Commentary Prompts with Copilot in Excel (or another AI assistant) to generate a written summary for stakeholders.
A25: Important Notes
A26: This template ships with illustrative sample data so you can see how the model behaves — replace it with your own figures before relying on it for real decisions.
A27: “Live” updating means designing a refresh process (see the Live Data Connection Guide tab) — this workbook does not automatically pull data from your bank without that setup.
A29: © 2026 MDD Business Consulting · Premium Resource · Not for redistribution.

Sheet Scenario Inputs
A1: Scenario Inputs
A2: Set your Best / Base / Worst case assumptions here. The 13-Week Cash Flow tab pulls whichever scenario is selected there.
A4: Starting Cash Balance ($) | B4: 185000
A5: Base Weekly Sales ($) — current week level | B5: 120000
A7: Assumption | B7: Best Case | C7: Base Case | D7: Worst Case
A8: Weekly Revenue Growth Rate (%) | B8: 0.02 | C8: 0.005 | D8: -0.03
A9: Collection Rate — Same Week (%) | B9: 0.6 | C9: 0.45 | D9: 0.3
A10: Collection Rate — Week +1 Delay (%) | B10: 0.35 | C10: 0.4 | D10: 0.4
A11: Collection Rate — Week +2+ / Bad Debt (%) | B11: 0.05 | C11: 0.15 | D11: 0.3
A12: Payroll & Fixed Cost Growth (%) | B12: 0 | C12: 0.005 | D12: 0.015
A13: COGS / Supplier Payment Ratio (%) | B13: 0.4 | C13: 0.45 | D13: 0.5
A14: Discretionary Spend Multiplier | B14: 1.05 | C14: 1 | D14: 0.8
A15: Minimum Cash Threshold ($) | B15: 160000 | C15: 160000 | D15: 160000
A17: Collection Rate Check (should total 100%) | B17: =SUM(B9:B11) -> 1 | C17: =SUM(C9:C11) -> 1 | D17: =SUM(D9:D11) -> 1

Sheet 13-Week Cash Flow
A1: 13-Week Rolling Cash Flow Forecast
A2: Active Scenario: | B2: Base Case | D2: Forecast Start Date: | E2: 46255
A4: ACTIVE SCENARIO ASSUMPTIONS (auto-pulled from Scenario Inputs based on the selector above)
A5: Weekly Revenue Growth Rate | B5: =INDEX('Scenario Inputs'!$B$8:$D$8,MATCH($B$2,'Scenario Inputs'!$B$7:$D$7,0)) -> 0.005
A6: Collection Rate — Same Week | B6: =INDEX('Scenario Inputs'!$B$9:$D$9,MATCH($B$2,'Scenario Inputs'!$B$7:$D$7,0)) -> 0.45
A7: Collection Rate — Week +1 Delay | B7: =INDEX('Scenario Inputs'!$B$10:$D$10,MATCH($B$2,'Scenario Inputs'!$B$7:$D$7,0)) -> 0.4
A8: Collection Rate — Week +2+ / Bad Debt | B8: =INDEX('Scenario Inputs'!$B$11:$D$11,MATCH($B$2,'Scenario Inputs'!$B$7:$D$7,0)) -> 0.15
A9: Payroll & Fixed Cost Growth | B9: =INDEX('Scenario Inputs'!$B$12:$D$12,MATCH($B$2,'Scenario Inputs'!$B$7:$D$7,0)) -> 0.005
A10: COGS / Supplier Payment Ratio | B10: =INDEX('Scenario Inputs'!$B$13:$D$13,MATCH($B$2,'Scenario Inputs'!$B$7:$D$7,0)) -> 0.45
A11: Discretionary Spend Multiplier | B11: =INDEX('Scenario Inputs'!$B$14:$D$14,MATCH($B$2,'Scenario Inputs'!$B$7:$D$7,0)) -> 1
A12: Minimum Cash Threshold | B12: =INDEX('Scenario Inputs'!$B$15:$D$15,MATCH($B$2,'Scenario Inputs'!$B$7:$D$7,0)) -> 160000
A14: 13-WEEK ROLLING FORECAST
A15: Week Starting | B15: =$E$2 -> 46255 | C15: =B15+7 -> 46262 | D15: =C15+7 -> 46269 | E15: =D15+7 -> 46276 | F15: =E15+7 -> 46283 | G15: =F15+7 -> 46290 | H15: =G15+7 -> 46297 | I15: =H15+7 -> 46304 | J15: =I15+7 -> 46311 | ... N15: =M15+7 -> 46339
A16: Week Number | B16: 1 | C16: =B16+1 -> 2 | D16: =C16+1 -> 3 | E16: =D16+1 -> 4 | F16: =E16+1 -> 5 | G16: =F16+1 -> 6 | H16: =G16+1 -> 7 | I16: =H16+1 -> 8 | J16: =I16+1 -> 9 | ... N16: =M16+1 -> 13
A18: CASH POSITION
A19: Opening Cash Balance | B19: ='Scenario Inputs'!$B$4 -> 185000 | C19: =B41 -> 190500 | D19: =C41 -> 196095 | E19: =D41 -> 201755.48 | F19: =E41 -> 207571.75 | G19: =F41 -> 213544.61 | H19: =G41 -> 204674.83 | I19: =H41 -> 210963.21 | J19: =I41 -> 217410.52 | ... N19: =M41 -> 236805.16
A21: CASH RECEIPTS
A22: Forecast Sales (Revenue) | B22: ='Scenario Inputs'!$B$5 -> 120000 | C22: =B22*(1+$B$5) -> 120600 | D22: =C22*(1+$B$5) -> 121203 | E22: =D22*(1+$B$5) -> 121809.01 | F22: =E22*(1+$B$5) -> 122418.06 | G22: =F22*(1+$B$5) -> 123030.15 | H22: =G22*(1+$B$5) -> 123645.3 | I22: =H22*(1+$B$5) -> 124263.53 | J22: =I22*(1+$B$5) -> 124884.85 | ... N22: =M22*(1+$B$5) -> 127401.34
A23: Collections — Same Week | B23: =B22*$B$6 -> 54000 | C23: =C22*$B$6 -> 54270 | D23: =D22*$B$6 -> 54541.35 | E23: =E22*$B$6 -> 54814.057 | F23: =F22*$B$6 -> 55088.127 | G23: =G22*$B$6 -> 55363.568 | H23: =H22*$B$6 -> 55640.386 | I23: =I22*$B$6 -> 55918.587 | ... N23: =N22*$B$6 -> 57330.602
A24: Collections — Week +1 Delay | B24: ='Scenario Inputs'!$B$5*$B$7 -> 48000 | C24: =B22*$B$7 -> 48000 | D24: =C22*$B$7 -> 48240 | E24: =D22*$B$7 -> 48481.2 | F24: =E22*$B$7 -> 48723.606 | G24: =F22*$B$7 -> 48967.224 | H24: =G22*$B$7 -> 49212.06 | I24: =H22*$B$7 -> 49458.12 | J24: =I22*$B$7 -> 49705.411 | ... N24: =M22*$B$7 -> 50707
A25: Collections — Week +2+ Delay | B25: ='Scenario Inputs'!$B$5*$B$8 -> 18000 | C25: ='Scenario Inputs'!$B$5*$B$8 -> 18000 | D25: =B22*$B$8 -> 18000 | E25: =C22*$B$8 -> 18090 | F25: =D22*$B$8 -> 18180.45 | G25: =E22*$B$8 -> 18271.352 | H25: =F22*$B$8 -> 18362.709 | I25: =G22*$B$8 -> 18454.523 | J25: =H22*$B$8 -> 18546.795 | K25: =I22*$B$8 -> 18639.529 | ... N25: =L22*$B$8 -> 18920.522
A26: Other Income | B26: 2000 | C26: 2000 | D26: 2000 | E26: 2000 | F26: 2000 | G26: 2000 | H26: 2000 | I26: 2000 | J26: 2000 | K26: 2000 | L26: 2000 | M26: 2000 | N26: 2000
A27: TOTAL CASH RECEIPTS | B27: =SUM(B23:B26) -> 122000 | C27: =SUM(C23:C26) -> 122270 | D27: =SUM(D23:D26) -> 122781.35 | E27: =SUM(E23:E26) -> 123385.26 | F27: =SUM(F23:F26) -> 123992.18 | G27: =SUM(G23:G26) -> 124602.14 | H27: =SUM(H23:H26) -> 125215.15 | I27: =SUM(I23:I26) -> 125831.23 | ... N27: =SUM(N23:N26) -> 128958.12
A29: CASH PAYMENTS
A30: Payroll & Benefits | B30: =35000 -> 35000 | C30: =B30*(1+$B$9) -> 35175 | D30: =C30*(1+$B$9) -> 35350.875 | E30: =D30*(1+$B$9) -> 35527.629 | F30: =E30*(1+$B$9) -> 35705.268 | G30: =F30*(1+$B$9) -> 35883.794 | H30: =G30*(1+$B$9) -> 36063.213 | I30: =H30*(1+$B$9) -> 36243.529 | J30: =I30*(1+$B$9) -> 36424.747 | ... N30: =M30*(1+$B$9) -> 37158.723
A31: Rent & Facilities | B31: 6000 | C31: 6000 | D31: 6000 | E31: 6000 | F31: 6000 | G31: 6000 | H31: 6000 | I31: 6000 | J31: 6000 | K31: 6000 | L31: 6000 | M31: 6000 | N31: 6000
A32: Supplier / COGS Payments | B32: ='Scenario Inputs'!$B$5*$B$10 -> 54000 | C32: =B22*$B$10 -> 54000 | D32: =C22*$B$10 -> 54270 | E32: =D22*$B$10 -> 54541.35 | F32: =E22*$B$10 -> 54814.057 | G32: =F22*$B$10 -> 55088.127 | H32: =G22*$B$10 -> 55363.568 | I32: =H22*$B$10 -> 55640.386 | J32: =I22*$B$10 -> 55918.587 | ... N32: =M22*$B$10 -> 57045.375
A33: Tax Payments | B33: 0 | C33: 0 | D33: 0 | E33: 0 | F33: 0 | G33: 15000 | H33: 0 | I33: 0 | J33: 0 | K33: 0 | L33: 0 | M33: 0 | N33: 0
A34: Loan / Debt Service | B34: 3500 | C34: 3500 | D34: 3500 | E34: 3500 | F34: 3500 | G34: 3500 | H34: 3500 | I34: 3500 | J34: 3500 | K34: 3500 | L34: 3500 | M34: 3500 | N34: 3500
A35: Other Operating Expenses | B35: =18000 -> 18000 | C35: =B35*$B$11 -> 18000 | D35: =C35*$B$11 -> 18000 | E35: =D35*$B$11 -> 18000 | F35: =E35*$B$11 -> 18000 | G35: =F35*$B$11 -> 18000 | H35: =G35*$B$11 -> 18000 | I35: =H35*$B$11 -> 18000 | J35: =I35*$B$11 -> 18000 | ... N35: =M35*$B$11 -> 18000
A36: Capital Expenditure | B36: 0 | C36: 0 | D36: 0 | E36: 0 | F36: 0 | G36: 0 | H36: 0 | I36: 0 | J36: 8000 | K36: 0 | L36: 0 | M36: 0 | N36: 0
A37: TOTAL CASH PAYMENTS | B37: =SUM(B30:B36) -> 116500 | C37: =SUM(C30:C36) -> 116675 | D37: =SUM(D30:D36) -> 117120.87 | E37: =SUM(E30:E36) -> 117568.98 | F37: =SUM(F30:F36) -> 118019.32 | G37: =SUM(G30:G36) -> 133471.92 | H37: =SUM(H30:H36) -> 118926.78 | I37: =SUM(I30:I36) -> 119383.91 | ... N37: =SUM(N30:N36) -> 121704.1
A39: NET CASH FLOW
A40: Net Cash Flow | B40: =B27-B37 -> 5500 | C40: =C27-C37 -> 5595 | D40: =D27-D37 -> 5660.475 | E40: =E27-E37 -> 5816.2774 | F40: =F27-F37 -> 5972.8588 | G40: =G27-G37 -> -8869.7769 | H40: =H27-H37 -> 6288.3742 | I40: =I27-I37 -> 6447.316 | ... N40: =N27-N37 -> 7254.0258
A41: Closing Cash Balance | B41: =B19+B40 -> 190500 | C41: =C19+C40 -> 196095 | D41: =D19+D40 -> 201755.48 | E41: =E19+E40 -> 207571.75 | F41: =F19+F40 -> 213544.61 | G41: =G19+G40 -> 204674.83 | H41: =H19+H40 -> 210963.21 | I41: =I19+I40 -> 217410.52 | ... N41: =N19+N40 -> 244059.19
A43: THRESHOLD & STATUS
A44: Minimum Cash Threshold | B44: =$B$12 -> 160000 | C44: =$B$12 -> 160000 | D44: =$B$12 -> 160000 | E44: =$B$12 -> 160000 | F44: =$B$12 -> 160000 | G44: =$B$12 -> 160000 | H44: =$B$12 -> 160000 | I44: =$B$12 -> 160000 | ... N44: =$B$12 -> 160000
A45: Buffer Above / (Below) Threshold | B45: =B41-B44 -> 30500 | C45: =C41-C44 -> 36095 | D45: =D41-D44 -> 41755.475 | E45: =E41-E44 -> 47571.752 | F45: =F41-F44 -> 53544.611 | G45: =G41-G44 -> 44674.834 | H45: =H41-H44 -> 50963.208 | I45: =I41-I44 -> 57410.524 | ... N45: =N41-N44 -> 84059.187
A46: Status | B46: =IF(B45<0,"Below Minimum",IF(B45<B44*0.2,"Near Minimum","Healthy")) -> Near Minimum | C46: =IF(C45<0,"Below Minimum",IF(C45<C44*0.2,"Near Minimum","Healthy")) -> Healthy | D46: =IF(D45<0,"Below Minimum",IF(D45<D44*0.2,"Near Minimum","Healthy")) -> Healthy | E46: =IF(E45<0,"Below Minimum",IF(E45<E44*0.2,"Near Minimum","Healthy")) -> Healthy | F46: =IF(F45<0,"Below Minimum",IF(F45<F44*0.2,"Near Minimum","Healthy")) -> Healthy | G46: =IF(G45<0,"Below Minimum",IF(G45<G44*0.2,"Near Minimum","Healthy")) -> Healthy | H46: =IF(H45<0,"Below Minimum",IF(H45<H44*0.2,"Near Minimum","Healthy")) -> Healthy | I46: =IF(I45<0,"Below Minimum",IF(I45<I44*0.2,"Near Minimum","Healthy")) -> Healthy | ... N46: =IF(N45<0,"Below Minimum",IF(N45<N44*0.2,"Near Minimum","Healthy")) -> Healthy

Sheet Anomaly Detection
A1: Anomaly Detection Dashboard
A2: Automatically flags any week in the 13-Week Cash Flow tab where projected cash falls below your minimum threshold, or shows an unusually large week-over-week swing.
A4: Week # | B4: Week Starting | C4: Closing Balance | D4: Min. Threshold | E4: Buffer | F4: Status | G4: Week-over-Week Change | H4: Change Flag
A5: ='13-Week Cash Flow'!B16 -> 1 | B5: ='13-Week Cash Flow'!B15 -> 46255 | C5: ='13-Week Cash Flow'!B41 -> 190500 | D5: ='13-Week Cash Flow'!B44 -> 160000 | E5: ='13-Week Cash Flow'!B45 -> 30500 | F5: ='13-Week Cash Flow'!B46 -> Near Minimum | G5: ='13-Week Cash Flow'!B41-'13-Week Cash Flow'!B19 -> 5500 | H5: =IF(ABS(G5)>D5*0.15,"Large Swing","")
A6: ='13-Week Cash Flow'!C16 -> 2 | B6: ='13-Week Cash Flow'!C15 -> 46262 | C6: ='13-Week Cash Flow'!C41 -> 196095 | D6: ='13-Week Cash Flow'!C44 -> 160000 | E6: ='13-Week Cash Flow'!C45 -> 36095 | F6: ='13-Week Cash Flow'!C46 -> Healthy | G6: ='13-Week Cash Flow'!C41-'13-Week Cash Flow'!B41 -> 5595 | H6: =IF(ABS(G6)>D6*0.15,"Large Swing","")
A7: ='13-Week Cash Flow'!D16 -> 3 | B7: ='13-Week Cash Flow'!D15 -> 46269 | C7: ='13-Week Cash Flow'!D41 -> 201755.48 | D7: ='13-Week Cash Flow'!D44 -> 160000 | E7: ='13-Week Cash Flow'!D45 -> 41755.475 | F7: ='13-Week Cash Flow'!D46 -> Healthy | G7: ='13-Week Cash Flow'!D41-'13-Week Cash Flow'!C41 -> 5660.475 | H7: =IF(ABS(G7)>D7*0.15,"Large Swing","")
A8: ='13-Week Cash Flow'!E16 -> 4 | B8: ='13-Week Cash Flow'!E15 -> 46276 | C8: ='13-Week Cash Flow'!E41 -> 207571.75 | D8: ='13-Week Cash Flow'!E44 -> 160000 | E8: ='13-Week Cash Flow'!E45 -> 47571.752 | F8: ='13-Week Cash Flow'!E46 -> Healthy | G8: ='13-Week Cash Flow'!E41-'13-Week Cash Flow'!D41 -> 5816.2774 | H8: =IF(ABS(G8)>D8*0.15,"Large Swing","")
A9: ='13-Week Cash Flow'!F16 -> 5 | B9: ='13-Week Cash Flow'!F15 -> 46283 | C9: ='13-Week Cash Flow'!F41 -> 213544.61 | D9: ='13-Week Cash Flow'!F44 -> 160000 | E9: ='13-Week Cash Flow'!F45 -> 53544.611 | F9: ='13-Week Cash Flow'!F46 -> Healthy | G9: ='13-Week Cash Flow'!F41-'13-Week Cash Flow'!E41 -> 5972.8588 | H9: =IF(ABS(G9)>D9*0.15,"Large Swing","")
A10: ='13-Week Cash Flow'!G16 -> 6 | B10: ='13-Week Cash Flow'!G15 -> 46290 | C10: ='13-Week Cash Flow'!G41 -> 204674.83 | D10: ='13-Week Cash Flow'!G44 -> 160000 | E10: ='13-Week Cash Flow'!G45 -> 44674.834 | F10: ='13-Week Cash Flow'!G46 -> Healthy | G10: ='13-Week Cash Flow'!G41-'13-Week Cash Flow'!F41 -> -8869.7769 | H10: =IF(ABS(G10)>D10*0.15,"Large Swing","")
A11: ='13-Week Cash Flow'!H16 -> 7 | B11: ='13-Week Cash Flow'!H15 -> 46297 | C11: ='13-Week Cash Flow'!H41 -> 210963.21 | D11: ='13-Week Cash Flow'!H44 -> 160000 | E11: ='13-Week Cash Flow'!H45 -> 50963.208 | F11: ='13-Week Cash Flow'!H46 -> Healthy | G11: ='13-Week Cash Flow'!H41-'13-Week Cash Flow'!G41 -> 6288.3742 | H11: =IF(ABS(G11)>D11*0.15,"Large Swing","")
A12: ='13-Week Cash Flow'!I16 -> 8 | B12: ='13-Week Cash Flow'!I15 -> 46304 | C12: ='13-Week Cash Flow'!I41 -> 217410.52 | D12: ='13-Week Cash Flow'!I44 -> 160000 | E12: ='13-Week Cash Flow'!I45 -> 57410.524 | F12: ='13-Week Cash Flow'!I46 -> Healthy | G12: ='13-Week Cash Flow'!I41-'13-Week Cash Flow'!H41 -> 6447.316 | H12: =IF(ABS(G12)>D12*0.15,"Large Swing","")
A13: ='13-Week Cash Flow'!J16 -> 9 | B13: ='13-Week Cash Flow'!J15 -> 46311 | C13: ='13-Week Cash Flow'!J41 -> 216017.58 | D13: ='13-Week Cash Flow'!J44 -> 160000 | E13: ='13-Week Cash Flow'!J45 -> 56017.577 | F13: ='13-Week Cash Flow'!J46 -> Healthy | G13: ='13-Week Cash Flow'!J41-'13-Week Cash Flow'!I41 -> -1392.9474 | H13: =IF(ABS(G13)>D13*0.15,"Large Swing","")
A14: ='13-Week Cash Flow'!K16 -> 10 | B14: ='13-Week Cash Flow'!K15 -> 46318 | C14: ='13-Week Cash Flow'!K41 -> 222785.16 | D14: ='13-Week Cash Flow'!K44 -> 160000 | E14: ='13-Week Cash Flow'!K45 -> 62785.165 | F14: ='13-Week Cash Flow'!K46 -> Healthy | G14: ='13-Week Cash Flow'!K41-'13-Week Cash Flow'!J41 -> 6767.5879 | H14: =IF(ABS(G14)>D14*0.15,"Large Swing","")
A15: ='13-Week Cash Flow'!L16 -> 11 | B15: ='13-Week Cash Flow'!L15 -> 46325 | C15: ='13-Week Cash Flow'!L41 -> 229714.09 | D15: ='13-Week Cash Flow'!L44 -> 160000 | E15: ='13-Week Cash Flow'!L45 -> 69714.091 | F15: ='13-Week Cash Flow'!L46 -> Healthy | G15: ='13-Week Cash Flow'!L41-'13-Week Cash Flow'!K41 -> 6928.9258 | H15: =IF(ABS(G15)>D15*0.15,"Large Swing","")
A16: ='13-Week Cash Flow'!M16 -> 12 | B16: ='13-Week Cash Flow'!M15 -> 46332 | C16: ='13-Week Cash Flow'!M41 -> 236805.16 | D16: ='13-Week Cash Flow'!M44 -> 160000 | E16: ='13-Week Cash Flow'!M45 -> 76805.161 | F16: ='13-Week Cash Flow'!M46 -> Healthy | G16: ='13-Week Cash Flow'!M41-'13-Week Cash Flow'!L41 -> 7091.0705 | H16: =IF(ABS(G16)>D16*0.15,"Large Swing","")
A17: ='13-Week Cash Flow'!N16 -> 13 | B17: ='13-Week Cash Flow'!N15 -> 46339 | C17: ='13-Week Cash Flow'!N41 -> 244059.19 | D17: ='13-Week Cash Flow'!N44 -> 160000 | E17: ='13-Week Cash Flow'!N45 -> 84059.187 | F17: ='13-Week Cash Flow'!N46 -> Healthy | G17: ='13-Week Cash Flow'!N41-'13-Week Cash Flow'!M41 -> 7254.0258 | H17: =IF(ABS(G17)>D17*0.15,"Large Swing","")
A19: SUMMARY
A20: Weeks Below Minimum Threshold: | D20: =COUNTIF(F5:F17,"Below Minimum") -> 0
A21: Weeks Near Minimum Threshold: | D21: =COUNTIF(F5:F17,"Near Minimum") -> 1
A22: Lowest Projected Closing Balance: | D22: =MIN(C5:C17) -> 190500
A23: Week of Lowest Balance: | D23: =INDEX(A5:A17,MATCH(MIN(C5:C17),C5:C17,0)) -> 1
A24: Largest Single-Week Negative Swing: | D24: =MIN(G5:G17) -> -8869.7769
A26: WHAT TO DO IF A WEEK IS FLAGGED
A27: – Accelerate collections on the largest outstanding invoices due before the flagged week.
A28: – Delay discretionary, non-essential spend scheduled for that week where possible.
A29: – Confirm whether a credit facility or overdraft is available to draw on as a buffer.
A30: – Escalate to management early — a flag with several weeks of notice is a planning problem, not a crisis.

Sheet Live Data Connection Guide
A1: Live Data Connection Guide
A2: This template works filled in manually, but the real value of a rolling 13-week forecast comes from connecting it to live bank and accounting data — so your Opening Balance and recent Sales/Payments update automatically each week rather than being retyped.
A4: Option 1 — Power Query From a Bank Export
A5: 1. Export recent transactions from your bank
A6: Most online banking portals support a CSV or Excel export under “Statements” or “Export” — grab the last few weeks.
A7: 2. Connect Excel to that file
A8: Data > Get Data > From File > From Workbook/CSV, and point it at your export.
A9: 3. Transform to the columns you need
A10: Use Power Query's transform steps to filter to the date range and columns required (date, amount, description).
A11: 4. Feed the result into Week 1's Opening Balance
A12: Load the query as a connection, then reference it in the Opening Balance formula instead of typing the figure manually.
A13: 5. Set it to refresh automatically
... A39: Whichever method you use: always sense-check the refreshed Opening Balance against your bank portal directly before trusting the model for a decision. An unnoticed connection failure will otherwise silently freeze last week's number in place.

Sheet AI Commentary Prompts
A1: AI Commentary Prompts
A2: Copy any of the prompts below into Copilot in Excel (or another AI assistant with access to this workbook) to generate narrative commentary from the model's current data. Adjust the bracketed details to match your actual audience and reporting cadence.
A4: Prompt 1 — Executive Summary
A5: “Using the data in the '13-Week Cash Flow' tab, write a 3-sentence executive summary of our projected cash position over the next 13 weeks under the Base Case scenario. Highlight the lowest projected balance and which week it occurs in.”
A7: Prompt 2 — Anomaly Explanation
A8: “Looking at the 'Anomaly Detection' tab, list every week flagged as Below Minimum or Near Minimum, and suggest two possible actions to address each one.”
A10: Prompt 3 — Scenario Comparison
A11: “Compare the Week 13 closing cash balance across the Best Case, Base Case, and Worst Case scenarios in this workbook, and explain in plain language what's driving the difference between them.”
A13: Prompt 4 — Board / Stakeholder Commentary
A14: “Write a short cash flow commentary suitable for a board pack, covering: our current cash position, the trend over the next 13 weeks, any weeks of concern, and what we're doing about them. Keep it under 150 words and avoid unexplained jargon.”
A16: Prompt 5 — Variance Explanation (once actuals are added)
A17: “Compare this week's actual cash receipts and payments in the '13-Week Cash Flow' tab against what was forecast for this week last month, and explain the most likely drivers of any significant variance.”
... A20: These prompts assume the AI assistant has access to read this workbook's current data (e.g. via Copilot in Excel's Agent Mode). If using a general-purpose AI tool without direct file access, copy the relevant figures into the chat alongside the prompt.
