Workbook

Sheet Instructions
A1: Finance Automation ROI Calculation Model
A2: The companion Excel model behind the Finance Automation Business Case Template — full cost, benefit, and sensitivity calculations.
A4: How This Workbook Is Organised
A5: – Current State Costs: What the manual process costs today — labour, errors, and any quantifiable opportunity cost.
A6: – Proposed Solution Costs: One-time Year 1 costs, ongoing annual costs, and any residual manual effort still required.
A7: – ROI Calculation: The core model — annual net savings, simple payback period, 3-year ROI, and NPV.
A8: – Sensitivity Analysis: Best / Base / Worst case scenarios so the business case doesn't rest on a single optimistic number.
A10: Colour Legend
A11: – Blue text = an input cell — replace with your own organisation's figures.
A12: – Black text = a formula — do not overtype, or the model will stop calculating correctly.
A13: – Green text = a link pulling data from another tab.
A15: Getting Started
... A25: A model is only as credible as its assumptions. Be prepared to explain where every input figure came from, not just what the final ROI percentage says.

Sheet Current State Costs
A1: Current State Costs
A2: What the manual process costs today. Every figure should be traceable to a real source, not a round estimate.
A4: Labour Cost
A5: Manual Hours per Week | B5: 8 | C5: e.g. from a time-tracking exercise
A6: Fully Loaded Hourly Rate ($) | B6: 55 | C6: include benefits/overhead, not just base pay
A7: Working Weeks per Year | B7: 48 | C7: accounting for holidays and PTO
A8: Annual Labour Cost | B8: =B5*B6*B7 -> 21120
A10: Other Current-State Costs
A11: Estimated Annual Error / Rework Cost | B11: 8000 | C11: cost of corrections, restatements, or write-offs
A12: Estimated Annual Opportunity Cost | B12: 5000 | C12: value of delayed decisions — leave as 0 if not quantifiable
A14: Total
A15: TOTAL CURRENT STATE ANNUAL COST | B15: =B8+B11+B12 -> 34120

Sheet Proposed Solution Costs
A1: Proposed Solution Costs
A2: One-time Year 1 costs, ongoing annual costs, and any residual manual effort still required after automation.
A4: Year 1 One-Time Costs
A5: Software / Licensing (Year 1) | B5: 6000 | C5: use a real vendor quote where possible
A6: Implementation | B6: 8000 | C6: internal hours + any external setup cost
A7: Training | B7: 3000 | C7: see the Training and Capability Building guidance elsewhere in this category
A8: TOTAL YEAR 1 ONE-TIME COST | B8: =B5+B6+B7 -> 17000
A10: Ongoing Annual Costs (Year 2+)
A11: Annual Licensing | B11: 6000
A12: Annual Governance / Maintenance | B12: 2400 | C12: monitoring, access reviews, periodic reassessment
A13: TOTAL ONGOING ANNUAL COST | B13: =B11+B12 -> 8400
A15: Residual Manual Effort (Post-Automation)
A16: Residual Hours per Week | B16: 2 | C16: manual review or exception-handling still needed
A17: Hourly Rate ($, linked) | B17: ='Current State Costs'!B6 -> 55
A18: Working Weeks per Year (linked) | B18: ='Current State Costs'!B7 -> 48
A19: RESIDUAL ANNUAL LABOUR COST | B19: =B16*B17*B18 -> 5280

Sheet ROI Calculation
A1: ROI Calculation
A2: Every figure below updates automatically from the Current State Costs and Proposed Solution Costs tabs.
A4: Key Inputs (Linked)
A5: Total Current State Annual Cost | B5: ='Current State Costs'!B15 -> 34120
A6: Total Year 1 One-Time Cost | B6: ='Proposed Solution Costs'!B8 -> 17000
A7: Total Ongoing Annual Cost (Year 2+) | B7: ='Proposed Solution Costs'!B13 -> 8400
A8: Residual Annual Labour Cost | B8: ='Proposed Solution Costs'!B19 -> 5280
A9: Discount Rate (for NPV) | B9: 0.08
A11: Steady-State Annual Savings
A12: Total Ongoing Cost After Automation | B12: =B7+B8 -> 13680
A13: ANNUAL NET SAVINGS (steady state) | B13: =B5-B12 -> 20440
A15: Payback Period
A16: SIMPLE PAYBACK PERIOD (months) | B16: =B6/(B13/12) -> 9.9804305
A18: 3-Year Cash Flow
B19: Year 1 | C19: Year 2 | D19: Year 3
A20: Total Cost | B20: =B6+B12 -> 30680 | C20: =B12 -> 13680 | D20: =B12 -> 13680
A21: Gross Savings (current-state cost avoided) | B21: =B5 -> 34120 | C21: =B5 -> 34120 | D21: =B5 -> 34120
A22: Net Cash Flow | B22: =B21-B20 -> 3440 | C22: =C21-C20 -> 20440 | D22: =D21-D20 -> 20440
A23: Cumulative Net Cash Flow | B23: =B22 -> 3440 | C23: =B23+C22 -> 23880 | D23: =C23+D22 -> 44320
A25: Headline Summary
A26: 3-YEAR ROI (%) | B26: =SUM(B22:D22)/SUM(B20:D20) -> 0.7636113
A27: NET PRESENT VALUE (NPV) | B27: =NPV(B9,B22:D22) -> 36935.122

Sheet Sensitivity Analysis
A1: Sensitivity Analysis
A2: The Base Case comes from the ROI Calculation tab. Best and Worst cases apply a savings-achievement rate — how much of the projected saving is actually realised in practice.
A4: Savings Achievement Rate (Input)
B5: Best Case | C5: Base Case | D5: Worst Case
A6: % of Projected Savings Achieved | B6: 1.1 | C6: 1 | D6: 0.7
A8: Resulting Figures
B9: Best Case | C9: Base Case | D9: Worst Case
A10: Adjusted Annual Net Savings | B10: ='ROI Calculation'!$B$13*B6 -> 22484 | C10: ='ROI Calculation'!$B$13*C6 -> 20440 | D10: ='ROI Calculation'!$B$13*D6 -> 14308
A11: Adjusted Payback Period (months) | B11: ='ROI Calculation'!$B$6/(B10/12) -> 9.0731187 | C11: ='ROI Calculation'!$B$6/(C10/12) -> 9.9804305 | D11: ='ROI Calculation'!$B$6/(D10/12) -> 14.257758
A12: Adjusted 3-Year ROI (%) | B12: =(3*B10-'ROI Calculation'!$B$6)/(('ROI Calculation'!$B$6+'ROI Calculation'!$C$20)+'ROI Calculation'!$C$20*2) -> 0.86926258 | C12: =(3*C10-'ROI Calculation'!$B$6)/(('ROI Calculation'!$B$6+'ROI Calculation'!$C$20)+'ROI Calculation'!$C$20*2) -> 0.7636113 | D12: =(3*D10-'ROI Calculation'!$B$6)/(('ROI Calculation'!$B$6+'ROI Calculation'!$C$20)+'ROI Calculation'!$C$20*2) -> 0.44665748
A14: Reading This Table
A15: Present the Base Case as your headline figure, but always know your Worst Case before presenting to a skeptical approver — a business case that only survives its best-case assumptions is not a robust one.
