Workbook

Sheet Setup
B2: T&E Vendor Evaluation Scorecard — Premium
B6: STEP 1 — ENTER VENDOR NAMES
B7: Vendor 1 | C7: Vendor 1
B8: Vendor 2 | C8: Vendor 2
B9: Vendor 3 | C9: Vendor 3
B10: Vendor 4 | C10: Vendor 4
B11: Vendor 5 | C11: Vendor 5
B12: Vendor 6 | C12: Vendor 6
B13: Vendor 7 | C13: Vendor 7
B14: Vendor 8 | C14: Vendor 8
B16: STEP 2 — SET DIMENSION WEIGHTS (must sum to 100%)
B17: 1. Functionality & Features | C17: 0.2
B18: 2. Integration & Technical Architecture | C18: 0.15
B19: 3. Implementation & Support | C19: 0.2
B20: 4. Commercial Terms | C20: 0.15
B21: 5. European Compliance | C21: 0.2
B22: 6. Vendor Viability & Strategic Fit | C22: 0.1
B23: Total (must = 100%) | C23: =SUM(C17:C22)
B25: INSTRUCTIONS
B27: 1. Enter vendor names in the yellow cells above (Step 1).
B28: 2. Adjust dimension weights if needed — they must sum to 100% (Step 2).
B29: 3. Go to the Scorecard sheet and score each vendor 0–5 for every criterion.
B30: 4. Criteria marked ★ are weighted 2x within their dimension.
B31: 5. The Summary sheet shows weighted scores, rankings, and a radar chart.
B32: 6. The Gap Analysis sheet highlights where each vendor falls short.
B34: Scoring guide:
B35: 0 = Not offered / fails requirement
B36: 1 = Poor — significant gaps
B37: 2 = Below average — notable gaps
B38: 3 = Acceptable — meets minimum requirements
... B40: 5 = Excellent — fully meets or exceeds

Sheet Scorecard
B2: T&E Vendor Evaluation Scorecard — Premium (60 criteria · 6 dimensions · up to 8 vendors)
C5: Criterion | D5: Wt | E5: =IF(Setup!C7="Vendor 1","Vendor 1",Setup!C7) | F5: =IF(Setup!C8="Vendor 2","Vendor 2",Setup!C8) | G5: =IF(Setup!C9="Vendor 3","Vendor 3",Setup!C9) | H5: =IF(Setup!C10="Vendor 4","Vendor 4",Setup!C10) | I5: =IF(Setup!C11="Vendor 5","Vendor 5",Setup!C11) | J5: =IF(Setup!C12="Vendor 6","Vendor 6",Setup!C12) | K5: =IF(Setup!C13="Vendor 7","Vendor 7",Setup!C13) | L5: =IF(Setup!C14="Vendor 8","Vendor 8",Setup!C14) | M5: Notes / Evidence
B7: # | C7: CRITERION | D7: WT | E7: V1 | F7: V2 | G7: V3 | H7: V4 | I7: V5 | J7: V6 | K7: V7 | L7: V8 | M7: NOTES
B8: 1. FUNCTIONALITY & FEATURES
B9: 1.01 | C9: Expense submission via mobile app (iOS & Android) ★ | D9: 2x
B10: 1.02 | C10: Receipt capture via OCR / AI photo scan ★ | D10: 2x
B11: 1.03 | C11: Multi-currency support and real-time exchange rate updates ★ | D11: 2x
B12: 1.04 | C12: Automated policy checking and real-time flagging ★ | D12: 2x
B13: 1.05 | C13: Configurable approval workflows (multi-level, threshold, entity) ★ | D13: 2x
B14: 1.06 | C14: Corporate card integration and automatic transaction import ★ | D14: 2x
B15: 1.07 | C15: Per diem and mileage calculation engine | D15: 1x
B16: 1.08 | C16: Offline mode for expense submission without connectivity | D16: 1x
B17: 1.09 | C17: Spend analytics and reporting dashboard | D17: 1x
B18: 1.10 | C18: Bulk approval and finance review workflows | D18: 1x
B19: 1.11 | C19: AI-powered duplicate expense detection | D19: 1x
B20: 1.12 | C20: Vendor / merchant category code management | D20: 1x
... B23: 1.15 | C23: Delegation / out-of-office approval routing | D23: 1x
B25: 2. INTEGRATION & TECHNICAL ARCHITECTURE
B26: 2.01 | C26: Native ERP connector (SAP S/4HANA, Dynamics 365, NetSuite, Oracle) ★ | D26: 2x
B27: 2.02 | C27: HRIS / payroll system integration (SAP HCM, Workday, BambooHR) ★ | D27: 2x
B28: 2.03 | C28: Corporate card provider integration (Amex, Visa, Mastercard GMS) ★ | D28: 2x
B29: 2.04 | C29: Travel booking tool integration (Concur Travel, Cytric, TravelPerk) | D29: 1x
B30: 2.05 | C30: REST API availability for custom integrations | D30: 1x
B31: 2.06 | C31: SSO / identity provider integration (Azure AD, Okta, Google) ★ | D31: 2x
B32: 2.07 | C32: Webhook / event-driven integration for real-time data flows | D32: 1x
B33: 2.08 | C33: Data export formats (CSV, XML, EDIFACT, custom flat file) | D33: 1x
B34: 2.09 | C34: Integration failure alerting and automated retry logic ★ | D34: 2x
B35: 2.10 | C35: Sandbox / non-production environment for testing integrations | D35: 1x
B37: 3. IMPLEMENTATION & SUPPORT
B38: 3.01 | C38: Dedicated implementation consultant assigned for programme duration ★ | D38: 2x
B39: 3.02 | C39: Structured methodology with defined phases and deliverables ★ | D39: 2x
B40: 3.03 | C40: Data migration support including historical data and mapping ★ | D40: 2x
B41: 3.04 | C41: Training materials in all required languages ★ | D41: 2x
B42: 3.05 | C42: Sandbox / UAT environment provided throughout implementation | D42: 1x
B43: 3.06 | C43: Post-go-live hypercare period (minimum 4 weeks defined in contract) ★ | D43: 2x
B44: 3.07 | C44: SLA for critical incident response — target < 4 hours | D44: 1x
B45: 3.08 | C45: Dedicated customer success manager post-go-live | D45: 1x
B46: 3.09 | C46: Community / knowledge base for self-service support | D46: 1x
B47: 3.10 | C47: References from comparable pan-European programmes ★ | D47: 2x
B49: 4. COMMERCIAL TERMS
B50: 4.01 | C50: Per-user pricing model — transparent and predictable ★ | D50: 2x
B51: 4.02 | C51: Contract allows entity / country additions without renegotiation ★ | D51: 2x
B52: 4.03 | C52: Exit clause — data export and transition support included ★ | D52: 2x
B53: 4.04 | C53: No hidden implementation or setup fees beyond quoted price ★ | D53: 2x
B54: 4.05 | C54: Multi-year discount and pricing lock available | D54: 1x
B55: 4.06 | C55: Vendor financial stability — established > 5 years | D55: 1x
B56: 4.07 | C56: Named account manager with defined response commitments | D56: 1x
B57: 4.08 | C57: Pilot / proof-of-concept pricing available pre-contract | D57: 1x
B58: 4.09 | C58: Penalty / SLA credit clause for go-live delay caused by vendor ★ | D58: 2x
B59: 4.10 | C59: Audit rights — right to inspect data processing practices | D59: 1x
B61: 5. EUROPEAN COMPLIANCE
B62: 5.01 | C62: GDPR compliance — data processed within EU / EEA by default ★ | D62: 2x
B63: 5.02 | C63: German receipt requirements (GoBD — digital archiving standards) ★ | D63: 2x
B64: 5.03 | C64: French per diem rules (URSSAF rates, domestic vs international) ★ | D64: 2x
B65: 5.04 | C65: Spanish IVA / VAT classification and deductibility ★ | D65: 2x
B66: 5.05 | C66: Dutch representation expense and 80% rule | D66: 1x
B67: 5.06 | C67: Works council / CSE information requirement support (France) | D67: 1x
B68: 5.07 | C68: Country-specific audit trail and archiving (10-year retention) ★ | D68: 2x
B69: 5.08 | C69: EU VAT reclaim support for cross-border business travel | D69: 1x
B70: 5.09 | C70: Italian SDI / e-invoicing compliance | D70: 1x
B71: 5.10 | C71: Belgian and Scandinavian market localisation | D71: 1x
B72: 5.11 | C72: Data residency options by country (for DE, FR data sovereignty) ★ | D72: 2x
B73: 5.12 | C73: DPIA / data processing agreement standard terms available | D73: 1x
B75: 6. VENDOR VIABILITY & STRATEGIC FIT
B76: 6.01 | C76: Product roadmap aligns with your organisation's 3-year technology strategy ★ | D76: 2x
B77: 6.02 | C77: Active investment in AI / automation features on the roadmap ★ | D77: 2x
B78: 6.03 | C78: Market presence and customer base in your target European countries ★ | D78: 2x
B79: 6.04 | C79: Analyst recognition (Gartner, Forrester, IDC coverage) | D79: 1x
B80: 6.05 | C80: Customer satisfaction scores / NPS publicly available or referenceable | D80: 1x
B81: 6.06 | C81: Acquisition / ownership stability — no pending M&A risk ★ | D81: 2x
B82: 6.07 | C82: Demonstrated experience in your industry vertical | D82: 1x
B83: 6.08 | C83: Partnership ecosystem (GSI, regional SI partners in your markets) | D83: 1x
C85: TOTAL WEIGHTED SCORE | E85: =IFERROR(SUMPRODUCT((D8:D83="2x")*ISNUMBER(E8:E83)*IF(ISNUMBER(E8:E83),E8:E83,0)*2)+SUMPRODUCT((D8:D83="1x")*ISNUMBER(E8:E83)*IF(ISNUMBER(E8:E83),E8:E83,0)),"") | F85: =IFERROR(SUMPRODUCT((D8:D83="2x")*ISNUMBER(F8:F83)*IF(ISNUMBER(F8:F83),F8:F83,0)*2)+SUMPRODUCT((D8:D83="1x")*ISNUMBER(F8:F83)*IF(ISNUMBER(F8:F83),F8:F83,0)),"") | G85: =IFERROR(SUMPRODUCT((D8:D83="2x")*ISNUMBER(G8:G83)*IF(ISNUMBER(G8:G83),G8:G83,0)*2)+SUMPRODUCT((D8:D83="1x")*ISNUMBER(G8:G83)*IF(ISNUMBER(G8:G83),G8:G83,0)),"") | H85: =IFERROR(SUMPRODUCT((D8:D83="2x")*ISNUMBER(H8:H83)*IF(ISNUMBER(H8:H83),H8:H83,0)*2)+SUMPRODUCT((D8:D83="1x")*ISNUMBER(H8:H83)*IF(ISNUMBER(H8:H83),H8:H83,0)),"") | I85: =IFERROR(SUMPRODUCT((D8:D83="2x")*ISNUMBER(I8:I83)*IF(ISNUMBER(I8:I83),I8:I83,0)*2)+SUMPRODUCT((D8:D83="1x")*ISNUMBER(I8:I83)*IF(ISNUMBER(I8:I83),I8:I83,0)),"") | J85: =IFERROR(SUMPRODUCT((D8:D83="2x")*ISNUMBER(J8:J83)*IF(ISNUMBER(J8:J83),J8:J83,0)*2)+SUMPRODUCT((D8:D83="1x")*ISNUMBER(J8:J83)*IF(ISNUMBER(J8:J83),J8:J83,0)),"") | K85: =IFERROR(SUMPRODUCT((D8:D83="2x")*ISNUMBER(K8:K83)*IF(ISNUMBER(K8:K83),K8:K83,0)*2)+SUMPRODUCT((D8:D83="1x")*ISNUMBER(K8:K83)*IF(ISNUMBER(K8:K83),K8:K83,0)),"") | L85: =IFERROR(SUMPRODUCT((D8:D83="2x")*ISNUMBER(L8:L83)*IF(ISNUMBER(L8:L83),L8:L83,0)*2)+SUMPRODUCT((D8:D83="1x")*ISNUMBER(L8:L83)*IF(ISNUMBER(L8:L83),L8:L83,0)),"")
C86: Maximum possible score: 490 (★ criteria count 2x)

Sheet Summary
B2: Vendor Evaluation Summary — Premium
B5: METRIC | C5: =IF(Setup!C7="Vendor 1","Vendor 1",Setup!C7) | D5: =IF(Setup!C8="Vendor 2","Vendor 2",Setup!C8) | E5: =IF(Setup!C9="Vendor 3","Vendor 3",Setup!C9) | F5: =IF(Setup!C10="Vendor 4","Vendor 4",Setup!C10) | G5: =IF(Setup!C11="Vendor 5","Vendor 5",Setup!C11) | H5: =IF(Setup!C12="Vendor 6","Vendor 6",Setup!C12) | I5: =IF(Setup!C13="Vendor 7","Vendor 7",Setup!C13) | J5: =IF(Setup!C14="Vendor 8","Vendor 8",Setup!C14)
B7: TOTAL WEIGHTED SCORE | C7: =Scorecard!E85 | D7: =Scorecard!F85 | E7: =Scorecard!G85 | F7: =Scorecard!H85 | G7: =Scorecard!I85 | H7: =Scorecard!J85 | I7: =Scorecard!K85 | J7: =Scorecard!L85
B8: Score as % of maximum | C8: =IFERROR(Scorecard!E85/490,"-") | D8: =IFERROR(Scorecard!F85/490,"-") | E8: =IFERROR(Scorecard!G85/490,"-") | F8: =IFERROR(Scorecard!H85/490,"-") | G8: =IFERROR(Scorecard!I85/490,"-") | H8: =IFERROR(Scorecard!J85/490,"-") | I8: =IFERROR(Scorecard!K85/490,"-") | J8: =IFERROR(Scorecard!L85/490,"-")
B9: Rank (1 = highest) | C9: =IFERROR(RANK(Scorecard!E85,(Scorecard!E85,Scorecard!F85,Scorecard!G85,Scorecard!H85,Scorecard!I85,Scorecard!J85,Scorecard!K85,Scorecard!L85),0),"-") | D9: =IFERROR(RANK(Scorecard!F85,(Scorecard!E85,Scorecard!F85,Scorecard!G85,Scorecard!H85,Scorecard!I85,Scorecard!J85,Scorecard!K85,Scorecard!L85),0),"-") | E9: =IFERROR(RANK(Scorecard!G85,(Scorecard!E85,Scorecard!F85,Scorecard!G85,Scorecard!H85,Scorecard!I85,Scorecard!J85,Scorecard!K85,Scorecard!L85),0),"-") | F9: =IFERROR(RANK(Scorecard!H85,(Scorecard!E85,Scorecard!F85,Scorecard!G85,Scorecard!H85,Scorecard!I85,Scorecard!J85,Scorecard!K85,Scorecard!L85),0),"-") | G9: =IFERROR(RANK(Scorecard!I85,(Scorecard!E85,Scorecard!F85,Scorecard!G85,Scorecard!H85,Scorecard!I85,Scorecard!J85,Scorecard!K85,Scorecard!L85),0),"-") | H9: =IFERROR(RANK(Scorecard!J85,(Scorecard!E85,Scorecard!F85,Scorecard!G85,Scorecard!H85,Scorecard!I85,Scorecard!J85,Scorecard!K85,Scorecard!L85),0),"-") | I9: =IFERROR(RANK(Scorecard!K85,(Scorecard!E85,Scorecard!F85,Scorecard!G85,Scorecard!H85,Scorecard!I85,Scorecard!J85,Scorecard!K85,Scorecard!L85),0),"-") | J9: =IFERROR(RANK(Scorecard!L85,(Scorecard!E85,Scorecard!F85,Scorecard!G85,Scorecard!H85,Scorecard!I85,Scorecard!J85,Scorecard!K85,Scorecard!L85),0),"-")
B11: SCORE BY DIMENSION
B12: 1. Functionality & Features | C12: =IFERROR(SUMPRODUCT((Scorecard!D9:D23="2x")*ISNUMBER(Scorecard!E9:Scorecard!E23)*IF(ISNUMBER(Scorecard!E9:Scorecard!E23),Scorecard!E9:Scorecard!E23,0)*2)+SUMPRODUCT((Scorecard!D9:D23="1x")*ISNUMBER(Scorecard!E9:Scorecard!E23)*IF(ISNUMBER(Scorecard!E9:Scorecard!E23),Scorecard!E9:Scorecard!E23,0)),"-") | D12: =IFERROR(SUMPRODUCT((Scorecard!D9:D23="2x")*ISNUMBER(Scorecard!F9:Scorecard!F23)*IF(ISNUMBER(Scorecard!F9:Scorecard!F23),Scorecard!F9:Scorecard!F23,0)*2)+SUMPRODUCT((Scorecard!D9:D23="1x")*ISNUMBER(Scorecard!F9:Scorecard!F23)*IF(ISNUMBER(Scorecard!F9:Scorecard!F23),Scorecard!F9:Scorecard!F23,0)),"-") | E12: =IFERROR(SUMPRODUCT((Scorecard!D9:D23="2x")*ISNUMBER(Scorecard!G9:Scorecard!G23)*IF(ISNUMBER(Scorecard!G9:Scorecard!G23),Scorecard!G9:Scorecard!G23,0)*2)+SUMPRODUCT((Scorecard!D9:D23="1x")*ISNUMBER(Scorecard!G9:Scorecard!G23)*IF(ISNUMBER(Scorecard!G9:Scorecard!G23),Scorecard!G9:Scorecard!G23,0)),"-") | F12: =IFERROR(SUMPRODUCT((Scorecard!D9:D23="2x")*ISNUMBER(Scorecard!H9:Scorecard!H23)*IF(ISNUMBER(Scorecard!H9:Scorecard!H23),Scorecard!H9:Scorecard!H23,0)*2)+SUMPRODUCT((Scorecard!D9:D23="1x")*ISNUMBER(Scorecard!H9:Scorecard!H23)*IF(ISNUMBER(Scorecard!H9:Scorecard!H23),Scorecard!H9:Scorecard!H23,0)),"-") | G12: =IFERROR(SUMPRODUCT((Scorecard!D9:D23="2x")*ISNUMBER(Scorecard!I9:Scorecard!I23)*IF(ISNUMBER(Scorecard!I9:Scorecard!I23),Scorecard!I9:Scorecard!I23,0)*2)+SUMPRODUCT((Scorecard!D9:D23="1x")*ISNUMBER(Scorecard!I9:Scorecard!I23)*IF(ISNUMBER(Scorecard!I9:Scorecard!I23),Scorecard!I9:Scorecard!I23,0)),"-") | H12: =IFERROR(SUMPRODUCT((Scorecard!D9:D23="2x")*ISNUMBER(Scorecard!J9:Scorecard!J23)*IF(ISNUMBER(Scorecard!J9:Scorecard!J23),Scorecard!J9:Scorecard!J23,0)*2)+SUMPRODUCT((Scorecard!D9:D23="1x")*ISNUMBER(Scorecard!J9:Scorecard!J23)*IF(ISNUMBER(Scorecard!J9:Scorecard!J23),Scorecard!J9:Scorecard!J23,0)),"-") | I12: =IFERROR(SUMPRODUCT((Scorecard!D9:D23="2x")*ISNUMBER(Scorecard!K9:Scorecard!K23)*IF(ISNUMBER(Scorecard!K9:Scorecard!K23),Scorecard!K9:Scorecard!K23,0)*2)+SUMPRODUCT((Scorecard!D9:D23="1x")*ISNUMBER(Scorecard!K9:Scorecard!K23)*IF(ISNUMBER(Scorecard!K9:Scorecard!K23),Scorecard!K9:Scorecard!K23,0)),"-") | J12: =IFERROR(SUMPRODUCT((Scorecard!D9:D23="2x")*ISNUMBER(Scorecard!L9:Scorecard!L23)*IF(ISNUMBER(Scorecard!L9:Scorecard!L23),Scorecard!L9:Scorecard!L23,0)*2)+SUMPRODUCT((Scorecard!D9:D23="1x")*ISNUMBER(Scorecard!L9:Scorecard!L23)*IF(ISNUMBER(Scorecard!L9:Scorecard!L23),Scorecard!L9:Scorecard!L23,0)),"-")
B13: 2. Integration & Technical Architecture | C13: =IFERROR(SUMPRODUCT((Scorecard!D26:D35="2x")*ISNUMBER(Scorecard!E26:Scorecard!E35)*IF(ISNUMBER(Scorecard!E26:Scorecard!E35),Scorecard!E26:Scorecard!E35,0)*2)+SUMPRODUCT((Scorecard!D26:D35="1x")*ISNUMBER(Scorecard!E26:Scorecard!E35)*IF(ISNUMBER(Scorecard!E26:Scorecard!E35),Scorecard!E26:Scorecard!E35,0)),"-") | D13: =IFERROR(SUMPRODUCT((Scorecard!D26:D35="2x")*ISNUMBER(Scorecard!F26:Scorecard!F35)*IF(ISNUMBER(Scorecard!F26:Scorecard!F35),Scorecard!F26:Scorecard!F35,0)*2)+SUMPRODUCT((Scorecard!D26:D35="1x")*ISNUMBER(Scorecard!F26:Scorecard!F35)*IF(ISNUMBER(Scorecard!F26:Scorecard!F35),Scorecard!F26:Scorecard!F35,0)),"-") | E13: =IFERROR(SUMPRODUCT((Scorecard!D26:D35="2x")*ISNUMBER(Scorecard!G26:Scorecard!G35)*IF(ISNUMBER(Scorecard!G26:Scorecard!G35),Scorecard!G26:Scorecard!G35,0)*2)+SUMPRODUCT((Scorecard!D26:D35="1x")*ISNUMBER(Scorecard!G26:Scorecard!G35)*IF(ISNUMBER(Scorecard!G26:Scorecard!G35),Scorecard!G26:Scorecard!G35,0)),"-") | F13: =IFERROR(SUMPRODUCT((Scorecard!D26:D35="2x")*ISNUMBER(Scorecard!H26:Scorecard!H35)*IF(ISNUMBER(Scorecard!H26:Scorecard!H35),Scorecard!H26:Scorecard!H35,0)*2)+SUMPRODUCT((Scorecard!D26:D35="1x")*ISNUMBER(Scorecard!H26:Scorecard!H35)*IF(ISNUMBER(Scorecard!H26:Scorecard!H35),Scorecard!H26:Scorecard!H35,0)),"-") | G13: =IFERROR(SUMPRODUCT((Scorecard!D26:D35="2x")*ISNUMBER(Scorecard!I26:Scorecard!I35)*IF(ISNUMBER(Scorecard!I26:Scorecard!I35),Scorecard!I26:Scorecard!I35,0)*2)+SUMPRODUCT((Scorecard!D26:D35="1x")*ISNUMBER(Scorecard!I26:Scorecard!I35)*IF(ISNUMBER(Scorecard!I26:Scorecard!I35),Scorecard!I26:Scorecard!I35,0)),"-") | H13: =IFERROR(SUMPRODUCT((Scorecard!D26:D35="2x")*ISNUMBER(Scorecard!J26:Scorecard!J35)*IF(ISNUMBER(Scorecard!J26:Scorecard!J35),Scorecard!J26:Scorecard!J35,0)*2)+SUMPRODUCT((Scorecard!D26:D35="1x")*ISNUMBER(Scorecard!J26:Scorecard!J35)*IF(ISNUMBER(Scorecard!J26:Scorecard!J35),Scorecard!J26:Scorecard!J35,0)),"-") | I13: =IFERROR(SUMPRODUCT((Scorecard!D26:D35="2x")*ISNUMBER(Scorecard!K26:Scorecard!K35)*IF(ISNUMBER(Scorecard!K26:Scorecard!K35),Scorecard!K26:Scorecard!K35,0)*2)+SUMPRODUCT((Scorecard!D26:D35="1x")*ISNUMBER(Scorecard!K26:Scorecard!K35)*IF(ISNUMBER(Scorecard!K26:Scorecard!K35),Scorecard!K26:Scorecard!K35,0)),"-") | J13: =IFERROR(SUMPRODUCT((Scorecard!D26:D35="2x")*ISNUMBER(Scorecard!L26:Scorecard!L35)*IF(ISNUMBER(Scorecard!L26:Scorecard!L35),Scorecard!L26:Scorecard!L35,0)*2)+SUMPRODUCT((Scorecard!D26:D35="1x")*ISNUMBER(Scorecard!L26:Scorecard!L35)*IF(ISNUMBER(Scorecard!L26:Scorecard!L35),Scorecard!L26:Scorecard!L35,0)),"-")
B14: 3. Implementation & Support | C14: =IFERROR(SUMPRODUCT((Scorecard!D38:D47="2x")*ISNUMBER(Scorecard!E38:Scorecard!E47)*IF(ISNUMBER(Scorecard!E38:Scorecard!E47),Scorecard!E38:Scorecard!E47,0)*2)+SUMPRODUCT((Scorecard!D38:D47="1x")*ISNUMBER(Scorecard!E38:Scorecard!E47)*IF(ISNUMBER(Scorecard!E38:Scorecard!E47),Scorecard!E38:Scorecard!E47,0)),"-") | D14: =IFERROR(SUMPRODUCT((Scorecard!D38:D47="2x")*ISNUMBER(Scorecard!F38:Scorecard!F47)*IF(ISNUMBER(Scorecard!F38:Scorecard!F47),Scorecard!F38:Scorecard!F47,0)*2)+SUMPRODUCT((Scorecard!D38:D47="1x")*ISNUMBER(Scorecard!F38:Scorecard!F47)*IF(ISNUMBER(Scorecard!F38:Scorecard!F47),Scorecard!F38:Scorecard!F47,0)),"-") | E14: =IFERROR(SUMPRODUCT((Scorecard!D38:D47="2x")*ISNUMBER(Scorecard!G38:Scorecard!G47)*IF(ISNUMBER(Scorecard!G38:Scorecard!G47),Scorecard!G38:Scorecard!G47,0)*2)+SUMPRODUCT((Scorecard!D38:D47="1x")*ISNUMBER(Scorecard!G38:Scorecard!G47)*IF(ISNUMBER(Scorecard!G38:Scorecard!G47),Scorecard!G38:Scorecard!G47,0)),"-") | F14: =IFERROR(SUMPRODUCT((Scorecard!D38:D47="2x")*ISNUMBER(Scorecard!H38:Scorecard!H47)*IF(ISNUMBER(Scorecard!H38:Scorecard!H47),Scorecard!H38:Scorecard!H47,0)*2)+SUMPRODUCT((Scorecard!D38:D47="1x")*ISNUMBER(Scorecard!H38:Scorecard!H47)*IF(ISNUMBER(Scorecard!H38:Scorecard!H47),Scorecard!H38:Scorecard!H47,0)),"-") | G14: =IFERROR(SUMPRODUCT((Scorecard!D38:D47="2x")*ISNUMBER(Scorecard!I38:Scorecard!I47)*IF(ISNUMBER(Scorecard!I38:Scorecard!I47),Scorecard!I38:Scorecard!I47,0)*2)+SUMPRODUCT((Scorecard!D38:D47="1x")*ISNUMBER(Scorecard!I38:Scorecard!I47)*IF(ISNUMBER(Scorecard!I38:Scorecard!I47),Scorecard!I38:Scorecard!I47,0)),"-") | H14: =IFERROR(SUMPRODUCT((Scorecard!D38:D47="2x")*ISNUMBER(Scorecard!J38:Scorecard!J47)*IF(ISNUMBER(Scorecard!J38:Scorecard!J47),Scorecard!J38:Scorecard!J47,0)*2)+SUMPRODUCT((Scorecard!D38:D47="1x")*ISNUMBER(Scorecard!J38:Scorecard!J47)*IF(ISNUMBER(Scorecard!J38:Scorecard!J47),Scorecard!J38:Scorecard!J47,0)),"-") | I14: =IFERROR(SUMPRODUCT((Scorecard!D38:D47="2x")*ISNUMBER(Scorecard!K38:Scorecard!K47)*IF(ISNUMBER(Scorecard!K38:Scorecard!K47),Scorecard!K38:Scorecard!K47,0)*2)+SUMPRODUCT((Scorecard!D38:D47="1x")*ISNUMBER(Scorecard!K38:Scorecard!K47)*IF(ISNUMBER(Scorecard!K38:Scorecard!K47),Scorecard!K38:Scorecard!K47,0)),"-") | J14: =IFERROR(SUMPRODUCT((Scorecard!D38:D47="2x")*ISNUMBER(Scorecard!L38:Scorecard!L47)*IF(ISNUMBER(Scorecard!L38:Scorecard!L47),Scorecard!L38:Scorecard!L47,0)*2)+SUMPRODUCT((Scorecard!D38:D47="1x")*ISNUMBER(Scorecard!L38:Scorecard!L47)*IF(ISNUMBER(Scorecard!L38:Scorecard!L47),Scorecard!L38:Scorecard!L47,0)),"-")
B15: 4. Commercial Terms | C15: =IFERROR(SUMPRODUCT((Scorecard!D50:D59="2x")*ISNUMBER(Scorecard!E50:Scorecard!E59)*IF(ISNUMBER(Scorecard!E50:Scorecard!E59),Scorecard!E50:Scorecard!E59,0)*2)+SUMPRODUCT((Scorecard!D50:D59="1x")*ISNUMBER(Scorecard!E50:Scorecard!E59)*IF(ISNUMBER(Scorecard!E50:Scorecard!E59),Scorecard!E50:Scorecard!E59,0)),"-") | D15: =IFERROR(SUMPRODUCT((Scorecard!D50:D59="2x")*ISNUMBER(Scorecard!F50:Scorecard!F59)*IF(ISNUMBER(Scorecard!F50:Scorecard!F59),Scorecard!F50:Scorecard!F59,0)*2)+SUMPRODUCT((Scorecard!D50:D59="1x")*ISNUMBER(Scorecard!F50:Scorecard!F59)*IF(ISNUMBER(Scorecard!F50:Scorecard!F59),Scorecard!F50:Scorecard!F59,0)),"-") | E15: =IFERROR(SUMPRODUCT((Scorecard!D50:D59="2x")*ISNUMBER(Scorecard!G50:Scorecard!G59)*IF(ISNUMBER(Scorecard!G50:Scorecard!G59),Scorecard!G50:Scorecard!G59,0)*2)+SUMPRODUCT((Scorecard!D50:D59="1x")*ISNUMBER(Scorecard!G50:Scorecard!G59)*IF(ISNUMBER(Scorecard!G50:Scorecard!G59),Scorecard!G50:Scorecard!G59,0)),"-") | F15: =IFERROR(SUMPRODUCT((Scorecard!D50:D59="2x")*ISNUMBER(Scorecard!H50:Scorecard!H59)*IF(ISNUMBER(Scorecard!H50:Scorecard!H59),Scorecard!H50:Scorecard!H59,0)*2)+SUMPRODUCT((Scorecard!D50:D59="1x")*ISNUMBER(Scorecard!H50:Scorecard!H59)*IF(ISNUMBER(Scorecard!H50:Scorecard!H59),Scorecard!H50:Scorecard!H59,0)),"-") | G15: =IFERROR(SUMPRODUCT((Scorecard!D50:D59="2x")*ISNUMBER(Scorecard!I50:Scorecard!I59)*IF(ISNUMBER(Scorecard!I50:Scorecard!I59),Scorecard!I50:Scorecard!I59,0)*2)+SUMPRODUCT((Scorecard!D50:D59="1x")*ISNUMBER(Scorecard!I50:Scorecard!I59)*IF(ISNUMBER(Scorecard!I50:Scorecard!I59),Scorecard!I50:Scorecard!I59,0)),"-") | H15: =IFERROR(SUMPRODUCT((Scorecard!D50:D59="2x")*ISNUMBER(Scorecard!J50:Scorecard!J59)*IF(ISNUMBER(Scorecard!J50:Scorecard!J59),Scorecard!J50:Scorecard!J59,0)*2)+SUMPRODUCT((Scorecard!D50:D59="1x")*ISNUMBER(Scorecard!J50:Scorecard!J59)*IF(ISNUMBER(Scorecard!J50:Scorecard!J59),Scorecard!J50:Scorecard!J59,0)),"-") | I15: =IFERROR(SUMPRODUCT((Scorecard!D50:D59="2x")*ISNUMBER(Scorecard!K50:Scorecard!K59)*IF(ISNUMBER(Scorecard!K50:Scorecard!K59),Scorecard!K50:Scorecard!K59,0)*2)+SUMPRODUCT((Scorecard!D50:D59="1x")*ISNUMBER(Scorecard!K50:Scorecard!K59)*IF(ISNUMBER(Scorecard!K50:Scorecard!K59),Scorecard!K50:Scorecard!K59,0)),"-") | J15: =IFERROR(SUMPRODUCT((Scorecard!D50:D59="2x")*ISNUMBER(Scorecard!L50:Scorecard!L59)*IF(ISNUMBER(Scorecard!L50:Scorecard!L59),Scorecard!L50:Scorecard!L59,0)*2)+SUMPRODUCT((Scorecard!D50:D59="1x")*ISNUMBER(Scorecard!L50:Scorecard!L59)*IF(ISNUMBER(Scorecard!L50:Scorecard!L59),Scorecard!L50:Scorecard!L59,0)),"-")
B16: 5. European Compliance | C16: =IFERROR(SUMPRODUCT((Scorecard!D62:D73="2x")*ISNUMBER(Scorecard!E62:Scorecard!E73)*IF(ISNUMBER(Scorecard!E62:Scorecard!E73),Scorecard!E62:Scorecard!E73,0)*2)+SUMPRODUCT((Scorecard!D62:D73="1x")*ISNUMBER(Scorecard!E62:Scorecard!E73)*IF(ISNUMBER(Scorecard!E62:Scorecard!E73),Scorecard!E62:Scorecard!E73,0)),"-") | D16: =IFERROR(SUMPRODUCT((Scorecard!D62:D73="2x")*ISNUMBER(Scorecard!F62:Scorecard!F73)*IF(ISNUMBER(Scorecard!F62:Scorecard!F73),Scorecard!F62:Scorecard!F73,0)*2)+SUMPRODUCT((Scorecard!D62:D73="1x")*ISNUMBER(Scorecard!F62:Scorecard!F73)*IF(ISNUMBER(Scorecard!F62:Scorecard!F73),Scorecard!F62:Scorecard!F73,0)),"-") | E16: =IFERROR(SUMPRODUCT((Scorecard!D62:D73="2x")*ISNUMBER(Scorecard!G62:Scorecard!G73)*IF(ISNUMBER(Scorecard!G62:Scorecard!G73),Scorecard!G62:Scorecard!G73,0)*2)+SUMPRODUCT((Scorecard!D62:D73="1x")*ISNUMBER(Scorecard!G62:Scorecard!G73)*IF(ISNUMBER(Scorecard!G62:Scorecard!G73),Scorecard!G62:Scorecard!G73,0)),"-") | F16: =IFERROR(SUMPRODUCT((Scorecard!D62:D73="2x")*ISNUMBER(Scorecard!H62:Scorecard!H73)*IF(ISNUMBER(Scorecard!H62:Scorecard!H73),Scorecard!H62:Scorecard!H73,0)*2)+SUMPRODUCT((Scorecard!D62:D73="1x")*ISNUMBER(Scorecard!H62:Scorecard!H73)*IF(ISNUMBER(Scorecard!H62:Scorecard!H73),Scorecard!H62:Scorecard!H73,0)),"-") | G16: =IFERROR(SUMPRODUCT((Scorecard!D62:D73="2x")*ISNUMBER(Scorecard!I62:Scorecard!I73)*IF(ISNUMBER(Scorecard!I62:Scorecard!I73),Scorecard!I62:Scorecard!I73,0)*2)+SUMPRODUCT((Scorecard!D62:D73="1x")*ISNUMBER(Scorecard!I62:Scorecard!I73)*IF(ISNUMBER(Scorecard!I62:Scorecard!I73),Scorecard!I62:Scorecard!I73,0)),"-") | H16: =IFERROR(SUMPRODUCT((Scorecard!D62:D73="2x")*ISNUMBER(Scorecard!J62:Scorecard!J73)*IF(ISNUMBER(Scorecard!J62:Scorecard!J73),Scorecard!J62:Scorecard!J73,0)*2)+SUMPRODUCT((Scorecard!D62:D73="1x")*ISNUMBER(Scorecard!J62:Scorecard!J73)*IF(ISNUMBER(Scorecard!J62:Scorecard!J73),Scorecard!J62:Scorecard!J73,0)),"-") | I16: =IFERROR(SUMPRODUCT((Scorecard!D62:D73="2x")*ISNUMBER(Scorecard!K62:Scorecard!K73)*IF(ISNUMBER(Scorecard!K62:Scorecard!K73),Scorecard!K62:Scorecard!K73,0)*2)+SUMPRODUCT((Scorecard!D62:D73="1x")*ISNUMBER(Scorecard!K62:Scorecard!K73)*IF(ISNUMBER(Scorecard!K62:Scorecard!K73),Scorecard!K62:Scorecard!K73,0)),"-") | J16: =IFERROR(SUMPRODUCT((Scorecard!D62:D73="2x")*ISNUMBER(Scorecard!L62:Scorecard!L73)*IF(ISNUMBER(Scorecard!L62:Scorecard!L73),Scorecard!L62:Scorecard!L73,0)*2)+SUMPRODUCT((Scorecard!D62:D73="1x")*ISNUMBER(Scorecard!L62:Scorecard!L73)*IF(ISNUMBER(Scorecard!L62:Scorecard!L73),Scorecard!L62:Scorecard!L73,0)),"-")
B17: 6. Vendor Viability & Strategic Fit | C17: =IFERROR(SUMPRODUCT((Scorecard!D76:D83="2x")*ISNUMBER(Scorecard!E76:Scorecard!E83)*IF(ISNUMBER(Scorecard!E76:Scorecard!E83),Scorecard!E76:Scorecard!E83,0)*2)+SUMPRODUCT((Scorecard!D76:D83="1x")*ISNUMBER(Scorecard!E76:Scorecard!E83)*IF(ISNUMBER(Scorecard!E76:Scorecard!E83),Scorecard!E76:Scorecard!E83,0)),"-") | D17: =IFERROR(SUMPRODUCT((Scorecard!D76:D83="2x")*ISNUMBER(Scorecard!F76:Scorecard!F83)*IF(ISNUMBER(Scorecard!F76:Scorecard!F83),Scorecard!F76:Scorecard!F83,0)*2)+SUMPRODUCT((Scorecard!D76:D83="1x")*ISNUMBER(Scorecard!F76:Scorecard!F83)*IF(ISNUMBER(Scorecard!F76:Scorecard!F83),Scorecard!F76:Scorecard!F83,0)),"-") | E17: =IFERROR(SUMPRODUCT((Scorecard!D76:D83="2x")*ISNUMBER(Scorecard!G76:Scorecard!G83)*IF(ISNUMBER(Scorecard!G76:Scorecard!G83),Scorecard!G76:Scorecard!G83,0)*2)+SUMPRODUCT((Scorecard!D76:D83="1x")*ISNUMBER(Scorecard!G76:Scorecard!G83)*IF(ISNUMBER(Scorecard!G76:Scorecard!G83),Scorecard!G76:Scorecard!G83,0)),"-") | F17: =IFERROR(SUMPRODUCT((Scorecard!D76:D83="2x")*ISNUMBER(Scorecard!H76:Scorecard!H83)*IF(ISNUMBER(Scorecard!H76:Scorecard!H83),Scorecard!H76:Scorecard!H83,0)*2)+SUMPRODUCT((Scorecard!D76:D83="1x")*ISNUMBER(Scorecard!H76:Scorecard!H83)*IF(ISNUMBER(Scorecard!H76:Scorecard!H83),Scorecard!H76:Scorecard!H83,0)),"-") | G17: =IFERROR(SUMPRODUCT((Scorecard!D76:D83="2x")*ISNUMBER(Scorecard!I76:Scorecard!I83)*IF(ISNUMBER(Scorecard!I76:Scorecard!I83),Scorecard!I76:Scorecard!I83,0)*2)+SUMPRODUCT((Scorecard!D76:D83="1x")*ISNUMBER(Scorecard!I76:Scorecard!I83)*IF(ISNUMBER(Scorecard!I76:Scorecard!I83),Scorecard!I76:Scorecard!I83,0)),"-") | H17: =IFERROR(SUMPRODUCT((Scorecard!D76:D83="2x")*ISNUMBER(Scorecard!J76:Scorecard!J83)*IF(ISNUMBER(Scorecard!J76:Scorecard!J83),Scorecard!J76:Scorecard!J83,0)*2)+SUMPRODUCT((Scorecard!D76:D83="1x")*ISNUMBER(Scorecard!J76:Scorecard!J83)*IF(ISNUMBER(Scorecard!J76:Scorecard!J83),Scorecard!J76:Scorecard!J83,0)),"-") | I17: =IFERROR(SUMPRODUCT((Scorecard!D76:D83="2x")*ISNUMBER(Scorecard!K76:Scorecard!K83)*IF(ISNUMBER(Scorecard!K76:Scorecard!K83),Scorecard!K76:Scorecard!K83,0)*2)+SUMPRODUCT((Scorecard!D76:D83="1x")*ISNUMBER(Scorecard!K76:Scorecard!K83)*IF(ISNUMBER(Scorecard!K76:Scorecard!K83),Scorecard!K76:Scorecard!K83,0)),"-") | J17: =IFERROR(SUMPRODUCT((Scorecard!D76:D83="2x")*ISNUMBER(Scorecard!L76:Scorecard!L83)*IF(ISNUMBER(Scorecard!L76:Scorecard!L83),Scorecard!L76:Scorecard!L83,0)*2)+SUMPRODUCT((Scorecard!D76:D83="1x")*ISNUMBER(Scorecard!L76:Scorecard!L83)*IF(ISNUMBER(Scorecard!L76:Scorecard!L83),Scorecard!L76:Scorecard!L83,0)),"-")
B19: DIMENSION-WEIGHTED COMPOSITE SCORE (using weights from Setup sheet)
B20: Composite score (0–100) | C20: =IFERROR((Setup!C17*IF(ISNUMBER(C12),C12/110*100,0))+(Setup!C18*IF(ISNUMBER(C13),C13/75*100,0))+(Setup!C19*IF(ISNUMBER(C14),C14/80*100,0))+(Setup!C20*IF(ISNUMBER(C15),C15/75*100,0))+(Setup!C21*IF(ISNUMBER(C16),C16/90*100,0))+(Setup!C22*IF(ISNUMBER(C17),C17/60*100,0)),"-") | D20: =IFERROR((Setup!C17*IF(ISNUMBER(D12),D12/110*100,0))+(Setup!C18*IF(ISNUMBER(D13),D13/75*100,0))+(Setup!C19*IF(ISNUMBER(D14),D14/80*100,0))+(Setup!C20*IF(ISNUMBER(D15),D15/75*100,0))+(Setup!C21*IF(ISNUMBER(D16),D16/90*100,0))+(Setup!C22*IF(ISNUMBER(D17),D17/60*100,0)),"-") | E20: =IFERROR((Setup!C17*IF(ISNUMBER(E12),E12/110*100,0))+(Setup!C18*IF(ISNUMBER(E13),E13/75*100,0))+(Setup!C19*IF(ISNUMBER(E14),E14/80*100,0))+(Setup!C20*IF(ISNUMBER(E15),E15/75*100,0))+(Setup!C21*IF(ISNUMBER(E16),E16/90*100,0))+(Setup!C22*IF(ISNUMBER(E17),E17/60*100,0)),"-") | F20: =IFERROR((Setup!C17*IF(ISNUMBER(F12),F12/110*100,0))+(Setup!C18*IF(ISNUMBER(F13),F13/75*100,0))+(Setup!C19*IF(ISNUMBER(F14),F14/80*100,0))+(Setup!C20*IF(ISNUMBER(F15),F15/75*100,0))+(Setup!C21*IF(ISNUMBER(F16),F16/90*100,0))+(Setup!C22*IF(ISNUMBER(F17),F17/60*100,0)),"-") | G20: =IFERROR((Setup!C17*IF(ISNUMBER(G12),G12/110*100,0))+(Setup!C18*IF(ISNUMBER(G13),G13/75*100,0))+(Setup!C19*IF(ISNUMBER(G14),G14/80*100,0))+(Setup!C20*IF(ISNUMBER(G15),G15/75*100,0))+(Setup!C21*IF(ISNUMBER(G16),G16/90*100,0))+(Setup!C22*IF(ISNUMBER(G17),G17/60*100,0)),"-") | H20: =IFERROR((Setup!C17*IF(ISNUMBER(H12),H12/110*100,0))+(Setup!C18*IF(ISNUMBER(H13),H13/75*100,0))+(Setup!C19*IF(ISNUMBER(H14),H14/80*100,0))+(Setup!C20*IF(ISNUMBER(H15),H15/75*100,0))+(Setup!C21*IF(ISNUMBER(H16),H16/90*100,0))+(Setup!C22*IF(ISNUMBER(H17),H17/60*100,0)),"-") | I20: =IFERROR((Setup!C17*IF(ISNUMBER(I12),I12/110*100,0))+(Setup!C18*IF(ISNUMBER(I13),I13/75*100,0))+(Setup!C19*IF(ISNUMBER(I14),I14/80*100,0))+(Setup!C20*IF(ISNUMBER(I15),I15/75*100,0))+(Setup!C21*IF(ISNUMBER(I16),I16/90*100,0))+(Setup!C22*IF(ISNUMBER(I17),I17/60*100,0)),"-") | J20: =IFERROR((Setup!C17*IF(ISNUMBER(J12),J12/110*100,0))+(Setup!C18*IF(ISNUMBER(J13),J13/75*100,0))+(Setup!C19*IF(ISNUMBER(J14),J14/80*100,0))+(Setup!C20*IF(ISNUMBER(J15),J15/75*100,0))+(Setup!C21*IF(ISNUMBER(J16),J16/90*100,0))+(Setup!C22*IF(ISNUMBER(J17),J17/60*100,0)),"-")
B22: RECOMMENDATION
B23: Add your recommendation and rationale here.

Sheet Gap Analysis
B2: Gap Analysis — Criteria Scoring Below Threshold
B5: Red = score 0–1 (fails/poor) · Amber = score 2–3 (gaps) · Green = score 4–5 (strong) · Grey = not yet scored
B7: # | C7: CRITERION | D7: WT | E7: V1 | F7: V2 | G7: V3 | H7: V4 | I7: V5 | J7: V6 | K7: V7 | L7: V8
B8: 1. FUNCTIONALITY & FEATURES
B9: 1.01 | C9: Expense submission via mobile app (iOS & Android) ★ | D9: 2x | E9: =Scorecard!E9 | F9: =Scorecard!F9 | G9: =Scorecard!G9 | H9: =Scorecard!H9 | I9: =Scorecard!I9 | J9: =Scorecard!J9 | K9: =Scorecard!K9 | L9: =Scorecard!L9
B10: 1.02 | C10: Receipt capture via OCR / AI photo scan ★ | D10: 2x | E10: =Scorecard!E10 | F10: =Scorecard!F10 | G10: =Scorecard!G10 | H10: =Scorecard!H10 | I10: =Scorecard!I10 | J10: =Scorecard!J10 | K10: =Scorecard!K10 | L10: =Scorecard!L10
B11: 1.03 | C11: Multi-currency support and real-time exchange rate updates ★ | D11: 2x | E11: =Scorecard!E11 | F11: =Scorecard!F11 | G11: =Scorecard!G11 | H11: =Scorecard!H11 | I11: =Scorecard!I11 | J11: =Scorecard!J11 | K11: =Scorecard!K11 | L11: =Scorecard!L11
B12: 1.04 | C12: Automated policy checking and real-time flagging ★ | D12: 2x | E12: =Scorecard!E12 | F12: =Scorecard!F12 | G12: =Scorecard!G12 | H12: =Scorecard!H12 | I12: =Scorecard!I12 | J12: =Scorecard!J12 | K12: =Scorecard!K12 | L12: =Scorecard!L12
B13: 1.05 | C13: Configurable approval workflows (multi-level, threshold, entity) ★ | D13: 2x | E13: =Scorecard!E13 | F13: =Scorecard!F13 | G13: =Scorecard!G13 | H13: =Scorecard!H13 | I13: =Scorecard!I13 | J13: =Scorecard!J13 | K13: =Scorecard!K13 | L13: =Scorecard!L13
B14: 1.06 | C14: Corporate card integration and automatic transaction import ★ | D14: 2x | E14: =Scorecard!E14 | F14: =Scorecard!F14 | G14: =Scorecard!G14 | H14: =Scorecard!H14 | I14: =Scorecard!I14 | J14: =Scorecard!J14 | K14: =Scorecard!K14 | L14: =Scorecard!L14
B15: 1.07 | C15: Per diem and mileage calculation engine | D15: 1x | E15: =Scorecard!E15 | F15: =Scorecard!F15 | G15: =Scorecard!G15 | H15: =Scorecard!H15 | I15: =Scorecard!I15 | J15: =Scorecard!J15 | K15: =Scorecard!K15 | L15: =Scorecard!L15
B16: 1.08 | C16: Offline mode for expense submission without connectivity | D16: 1x | E16: =Scorecard!E16 | F16: =Scorecard!F16 | G16: =Scorecard!G16 | H16: =Scorecard!H16 | I16: =Scorecard!I16 | J16: =Scorecard!J16 | K16: =Scorecard!K16 | L16: =Scorecard!L16
B17: 1.09 | C17: Spend analytics and reporting dashboard | D17: 1x | E17: =Scorecard!E17 | F17: =Scorecard!F17 | G17: =Scorecard!G17 | H17: =Scorecard!H17 | I17: =Scorecard!I17 | J17: =Scorecard!J17 | K17: =Scorecard!K17 | L17: =Scorecard!L17
B18: 1.10 | C18: Bulk approval and finance review workflows | D18: 1x | E18: =Scorecard!E18 | F18: =Scorecard!F18 | G18: =Scorecard!G18 | H18: =Scorecard!H18 | I18: =Scorecard!I18 | J18: =Scorecard!J18 | K18: =Scorecard!K18 | L18: =Scorecard!L18
B19: 1.11 | C19: AI-powered duplicate expense detection | D19: 1x | E19: =Scorecard!E19 | F19: =Scorecard!F19 | G19: =Scorecard!G19 | H19: =Scorecard!H19 | I19: =Scorecard!I19 | J19: =Scorecard!J19 | K19: =Scorecard!K19 | L19: =Scorecard!L19
B20: 1.12 | C20: Vendor / merchant category code management | D20: 1x | E20: =Scorecard!E20 | F20: =Scorecard!F20 | G20: =Scorecard!G20 | H20: =Scorecard!H20 | I20: =Scorecard!I20 | J20: =Scorecard!J20 | K20: =Scorecard!K20 | L20: =Scorecard!L20
... B23: 1.15 | C23: Delegation / out-of-office approval routing | D23: 1x | E23: =Scorecard!E23 | F23: =Scorecard!F23 | G23: =Scorecard!G23 | H23: =Scorecard!H23 | I23: =Scorecard!I23 | J23: =Scorecard!J23 | K23: =Scorecard!K23 | L23: =Scorecard!L23
B25: 2. INTEGRATION & TECHNICAL ARCHITECTURE
B26: 2.01 | C26: Native ERP connector (SAP S/4HANA, Dynamics 365, NetSuite, Oracle) ★ | D26: 2x | E26: =Scorecard!E26 | F26: =Scorecard!F26 | G26: =Scorecard!G26 | H26: =Scorecard!H26 | I26: =Scorecard!I26 | J26: =Scorecard!J26 | K26: =Scorecard!K26 | L26: =Scorecard!L26
B27: 2.02 | C27: HRIS / payroll system integration (SAP HCM, Workday, BambooHR) ★ | D27: 2x | E27: =Scorecard!E27 | F27: =Scorecard!F27 | G27: =Scorecard!G27 | H27: =Scorecard!H27 | I27: =Scorecard!I27 | J27: =Scorecard!J27 | K27: =Scorecard!K27 | L27: =Scorecard!L27
B28: 2.03 | C28: Corporate card provider integration (Amex, Visa, Mastercard GMS) ★ | D28: 2x | E28: =Scorecard!E28 | F28: =Scorecard!F28 | G28: =Scorecard!G28 | H28: =Scorecard!H28 | I28: =Scorecard!I28 | J28: =Scorecard!J28 | K28: =Scorecard!K28 | L28: =Scorecard!L28
B29: 2.04 | C29: Travel booking tool integration (Concur Travel, Cytric, TravelPerk) | D29: 1x | E29: =Scorecard!E29 | F29: =Scorecard!F29 | G29: =Scorecard!G29 | H29: =Scorecard!H29 | I29: =Scorecard!I29 | J29: =Scorecard!J29 | K29: =Scorecard!K29 | L29: =Scorecard!L29
B30: 2.05 | C30: REST API availability for custom integrations | D30: 1x | E30: =Scorecard!E30 | F30: =Scorecard!F30 | G30: =Scorecard!G30 | H30: =Scorecard!H30 | I30: =Scorecard!I30 | J30: =Scorecard!J30 | K30: =Scorecard!K30 | L30: =Scorecard!L30
B31: 2.06 | C31: SSO / identity provider integration (Azure AD, Okta, Google) ★ | D31: 2x | E31: =Scorecard!E31 | F31: =Scorecard!F31 | G31: =Scorecard!G31 | H31: =Scorecard!H31 | I31: =Scorecard!I31 | J31: =Scorecard!J31 | K31: =Scorecard!K31 | L31: =Scorecard!L31
B32: 2.07 | C32: Webhook / event-driven integration for real-time data flows | D32: 1x | E32: =Scorecard!E32 | F32: =Scorecard!F32 | G32: =Scorecard!G32 | H32: =Scorecard!H32 | I32: =Scorecard!I32 | J32: =Scorecard!J32 | K32: =Scorecard!K32 | L32: =Scorecard!L32
B33: 2.08 | C33: Data export formats (CSV, XML, EDIFACT, custom flat file) | D33: 1x | E33: =Scorecard!E33 | F33: =Scorecard!F33 | G33: =Scorecard!G33 | H33: =Scorecard!H33 | I33: =Scorecard!I33 | J33: =Scorecard!J33 | K33: =Scorecard!K33 | L33: =Scorecard!L33
B34: 2.09 | C34: Integration failure alerting and automated retry logic ★ | D34: 2x | E34: =Scorecard!E34 | F34: =Scorecard!F34 | G34: =Scorecard!G34 | H34: =Scorecard!H34 | I34: =Scorecard!I34 | J34: =Scorecard!J34 | K34: =Scorecard!K34 | L34: =Scorecard!L34
B35: 2.10 | C35: Sandbox / non-production environment for testing integrations | D35: 1x | E35: =Scorecard!E35 | F35: =Scorecard!F35 | G35: =Scorecard!G35 | H35: =Scorecard!H35 | I35: =Scorecard!I35 | J35: =Scorecard!J35 | K35: =Scorecard!K35 | L35: =Scorecard!L35
B37: 3. IMPLEMENTATION & SUPPORT
B38: 3.01 | C38: Dedicated implementation consultant assigned for programme duration ★ | D38: 2x | E38: =Scorecard!E38 | F38: =Scorecard!F38 | G38: =Scorecard!G38 | H38: =Scorecard!H38 | I38: =Scorecard!I38 | J38: =Scorecard!J38 | K38: =Scorecard!K38 | L38: =Scorecard!L38
B39: 3.02 | C39: Structured methodology with defined phases and deliverables ★ | D39: 2x | E39: =Scorecard!E39 | F39: =Scorecard!F39 | G39: =Scorecard!G39 | H39: =Scorecard!H39 | I39: =Scorecard!I39 | J39: =Scorecard!J39 | K39: =Scorecard!K39 | L39: =Scorecard!L39
B40: 3.03 | C40: Data migration support including historical data and mapping ★ | D40: 2x | E40: =Scorecard!E40 | F40: =Scorecard!F40 | G40: =Scorecard!G40 | H40: =Scorecard!H40 | I40: =Scorecard!I40 | J40: =Scorecard!J40 | K40: =Scorecard!K40 | L40: =Scorecard!L40
B41: 3.04 | C41: Training materials in all required languages ★ | D41: 2x | E41: =Scorecard!E41 | F41: =Scorecard!F41 | G41: =Scorecard!G41 | H41: =Scorecard!H41 | I41: =Scorecard!I41 | J41: =Scorecard!J41 | K41: =Scorecard!K41 | L41: =Scorecard!L41
B42: 3.05 | C42: Sandbox / UAT environment provided throughout implementation | D42: 1x | E42: =Scorecard!E42 | F42: =Scorecard!F42 | G42: =Scorecard!G42 | H42: =Scorecard!H42 | I42: =Scorecard!I42 | J42: =Scorecard!J42 | K42: =Scorecard!K42 | L42: =Scorecard!L42
B43: 3.06 | C43: Post-go-live hypercare period (minimum 4 weeks defined in contract) ★ | D43: 2x | E43: =Scorecard!E43 | F43: =Scorecard!F43 | G43: =Scorecard!G43 | H43: =Scorecard!H43 | I43: =Scorecard!I43 | J43: =Scorecard!J43 | K43: =Scorecard!K43 | L43: =Scorecard!L43
B44: 3.07 | C44: SLA for critical incident response — target < 4 hours | D44: 1x | E44: =Scorecard!E44 | F44: =Scorecard!F44 | G44: =Scorecard!G44 | H44: =Scorecard!H44 | I44: =Scorecard!I44 | J44: =Scorecard!J44 | K44: =Scorecard!K44 | L44: =Scorecard!L44
B45: 3.08 | C45: Dedicated customer success manager post-go-live | D45: 1x | E45: =Scorecard!E45 | F45: =Scorecard!F45 | G45: =Scorecard!G45 | H45: =Scorecard!H45 | I45: =Scorecard!I45 | J45: =Scorecard!J45 | K45: =Scorecard!K45 | L45: =Scorecard!L45
B46: 3.09 | C46: Community / knowledge base for self-service support | D46: 1x | E46: =Scorecard!E46 | F46: =Scorecard!F46 | G46: =Scorecard!G46 | H46: =Scorecard!H46 | I46: =Scorecard!I46 | J46: =Scorecard!J46 | K46: =Scorecard!K46 | L46: =Scorecard!L46
B47: 3.10 | C47: References from comparable pan-European programmes ★ | D47: 2x | E47: =Scorecard!E47 | F47: =Scorecard!F47 | G47: =Scorecard!G47 | H47: =Scorecard!H47 | I47: =Scorecard!I47 | J47: =Scorecard!J47 | K47: =Scorecard!K47 | L47: =Scorecard!L47
B49: 4. COMMERCIAL TERMS
B50: 4.01 | C50: Per-user pricing model — transparent and predictable ★ | D50: 2x | E50: =Scorecard!E50 | F50: =Scorecard!F50 | G50: =Scorecard!G50 | H50: =Scorecard!H50 | I50: =Scorecard!I50 | J50: =Scorecard!J50 | K50: =Scorecard!K50 | L50: =Scorecard!L50
B51: 4.02 | C51: Contract allows entity / country additions without renegotiation ★ | D51: 2x | E51: =Scorecard!E51 | F51: =Scorecard!F51 | G51: =Scorecard!G51 | H51: =Scorecard!H51 | I51: =Scorecard!I51 | J51: =Scorecard!J51 | K51: =Scorecard!K51 | L51: =Scorecard!L51
B52: 4.03 | C52: Exit clause — data export and transition support included ★ | D52: 2x | E52: =Scorecard!E52 | F52: =Scorecard!F52 | G52: =Scorecard!G52 | H52: =Scorecard!H52 | I52: =Scorecard!I52 | J52: =Scorecard!J52 | K52: =Scorecard!K52 | L52: =Scorecard!L52
B53: 4.04 | C53: No hidden implementation or setup fees beyond quoted price ★ | D53: 2x | E53: =Scorecard!E53 | F53: =Scorecard!F53 | G53: =Scorecard!G53 | H53: =Scorecard!H53 | I53: =Scorecard!I53 | J53: =Scorecard!J53 | K53: =Scorecard!K53 | L53: =Scorecard!L53
B54: 4.05 | C54: Multi-year discount and pricing lock available | D54: 1x | E54: =Scorecard!E54 | F54: =Scorecard!F54 | G54: =Scorecard!G54 | H54: =Scorecard!H54 | I54: =Scorecard!I54 | J54: =Scorecard!J54 | K54: =Scorecard!K54 | L54: =Scorecard!L54
B55: 4.06 | C55: Vendor financial stability — established > 5 years | D55: 1x | E55: =Scorecard!E55 | F55: =Scorecard!F55 | G55: =Scorecard!G55 | H55: =Scorecard!H55 | I55: =Scorecard!I55 | J55: =Scorecard!J55 | K55: =Scorecard!K55 | L55: =Scorecard!L55
B56: 4.07 | C56: Named account manager with defined response commitments | D56: 1x | E56: =Scorecard!E56 | F56: =Scorecard!F56 | G56: =Scorecard!G56 | H56: =Scorecard!H56 | I56: =Scorecard!I56 | J56: =Scorecard!J56 | K56: =Scorecard!K56 | L56: =Scorecard!L56
B57: 4.08 | C57: Pilot / proof-of-concept pricing available pre-contract | D57: 1x | E57: =Scorecard!E57 | F57: =Scorecard!F57 | G57: =Scorecard!G57 | H57: =Scorecard!H57 | I57: =Scorecard!I57 | J57: =Scorecard!J57 | K57: =Scorecard!K57 | L57: =Scorecard!L57
B58: 4.09 | C58: Penalty / SLA credit clause for go-live delay caused by vendor ★ | D58: 2x | E58: =Scorecard!E58 | F58: =Scorecard!F58 | G58: =Scorecard!G58 | H58: =Scorecard!H58 | I58: =Scorecard!I58 | J58: =Scorecard!J58 | K58: =Scorecard!K58 | L58: =Scorecard!L58
B59: 4.10 | C59: Audit rights — right to inspect data processing practices | D59: 1x | E59: =Scorecard!E59 | F59: =Scorecard!F59 | G59: =Scorecard!G59 | H59: =Scorecard!H59 | I59: =Scorecard!I59 | J59: =Scorecard!J59 | K59: =Scorecard!K59 | L59: =Scorecard!L59
B61: 5. EUROPEAN COMPLIANCE
B62: 5.01 | C62: GDPR compliance — data processed within EU / EEA by default ★ | D62: 2x | E62: =Scorecard!E62 | F62: =Scorecard!F62 | G62: =Scorecard!G62 | H62: =Scorecard!H62 | I62: =Scorecard!I62 | J62: =Scorecard!J62 | K62: =Scorecard!K62 | L62: =Scorecard!L62
B63: 5.02 | C63: German receipt requirements (GoBD — digital archiving standards) ★ | D63: 2x | E63: =Scorecard!E63 | F63: =Scorecard!F63 | G63: =Scorecard!G63 | H63: =Scorecard!H63 | I63: =Scorecard!I63 | J63: =Scorecard!J63 | K63: =Scorecard!K63 | L63: =Scorecard!L63
B64: 5.03 | C64: French per diem rules (URSSAF rates, domestic vs international) ★ | D64: 2x | E64: =Scorecard!E64 | F64: =Scorecard!F64 | G64: =Scorecard!G64 | H64: =Scorecard!H64 | I64: =Scorecard!I64 | J64: =Scorecard!J64 | K64: =Scorecard!K64 | L64: =Scorecard!L64
B65: 5.04 | C65: Spanish IVA / VAT classification and deductibility ★ | D65: 2x | E65: =Scorecard!E65 | F65: =Scorecard!F65 | G65: =Scorecard!G65 | H65: =Scorecard!H65 | I65: =Scorecard!I65 | J65: =Scorecard!J65 | K65: =Scorecard!K65 | L65: =Scorecard!L65
B66: 5.05 | C66: Dutch representation expense and 80% rule | D66: 1x | E66: =Scorecard!E66 | F66: =Scorecard!F66 | G66: =Scorecard!G66 | H66: =Scorecard!H66 | I66: =Scorecard!I66 | J66: =Scorecard!J66 | K66: =Scorecard!K66 | L66: =Scorecard!L66
B67: 5.06 | C67: Works council / CSE information requirement support (France) | D67: 1x | E67: =Scorecard!E67 | F67: =Scorecard!F67 | G67: =Scorecard!G67 | H67: =Scorecard!H67 | I67: =Scorecard!I67 | J67: =Scorecard!J67 | K67: =Scorecard!K67 | L67: =Scorecard!L67
B68: 5.07 | C68: Country-specific audit trail and archiving (10-year retention) ★ | D68: 2x | E68: =Scorecard!E68 | F68: =Scorecard!F68 | G68: =Scorecard!G68 | H68: =Scorecard!H68 | I68: =Scorecard!I68 | J68: =Scorecard!J68 | K68: =Scorecard!K68 | L68: =Scorecard!L68
B69: 5.08 | C69: EU VAT reclaim support for cross-border business travel | D69: 1x | E69: =Scorecard!E69 | F69: =Scorecard!F69 | G69: =Scorecard!G69 | H69: =Scorecard!H69 | I69: =Scorecard!I69 | J69: =Scorecard!J69 | K69: =Scorecard!K69 | L69: =Scorecard!L69
B70: 5.09 | C70: Italian SDI / e-invoicing compliance | D70: 1x | E70: =Scorecard!E70 | F70: =Scorecard!F70 | G70: =Scorecard!G70 | H70: =Scorecard!H70 | I70: =Scorecard!I70 | J70: =Scorecard!J70 | K70: =Scorecard!K70 | L70: =Scorecard!L70
B71: 5.10 | C71: Belgian and Scandinavian market localisation | D71: 1x | E71: =Scorecard!E71 | F71: =Scorecard!F71 | G71: =Scorecard!G71 | H71: =Scorecard!H71 | I71: =Scorecard!I71 | J71: =Scorecard!J71 | K71: =Scorecard!K71 | L71: =Scorecard!L71
B72: 5.11 | C72: Data residency options by country (for DE, FR data sovereignty) ★ | D72: 2x | E72: =Scorecard!E72 | F72: =Scorecard!F72 | G72: =Scorecard!G72 | H72: =Scorecard!H72 | I72: =Scorecard!I72 | J72: =Scorecard!J72 | K72: =Scorecard!K72 | L72: =Scorecard!L72
B73: 5.12 | C73: DPIA / data processing agreement standard terms available | D73: 1x | E73: =Scorecard!E73 | F73: =Scorecard!F73 | G73: =Scorecard!G73 | H73: =Scorecard!H73 | I73: =Scorecard!I73 | J73: =Scorecard!J73 | K73: =Scorecard!K73 | L73: =Scorecard!L73
B75: 6. VENDOR VIABILITY & STRATEGIC FIT
B76: 6.01 | C76: Product roadmap aligns with your organisation's 3-year technology strategy ★ | D76: 2x | E76: =Scorecard!E76 | F76: =Scorecard!F76 | G76: =Scorecard!G76 | H76: =Scorecard!H76 | I76: =Scorecard!I76 | J76: =Scorecard!J76 | K76: =Scorecard!K76 | L76: =Scorecard!L76
B77: 6.02 | C77: Active investment in AI / automation features on the roadmap ★ | D77: 2x | E77: =Scorecard!E77 | F77: =Scorecard!F77 | G77: =Scorecard!G77 | H77: =Scorecard!H77 | I77: =Scorecard!I77 | J77: =Scorecard!J77 | K77: =Scorecard!K77 | L77: =Scorecard!L77
B78: 6.03 | C78: Market presence and customer base in your target European countries ★ | D78: 2x | E78: =Scorecard!E78 | F78: =Scorecard!F78 | G78: =Scorecard!G78 | H78: =Scorecard!H78 | I78: =Scorecard!I78 | J78: =Scorecard!J78 | K78: =Scorecard!K78 | L78: =Scorecard!L78
B79: 6.04 | C79: Analyst recognition (Gartner, Forrester, IDC coverage) | D79: 1x | E79: =Scorecard!E79 | F79: =Scorecard!F79 | G79: =Scorecard!G79 | H79: =Scorecard!H79 | I79: =Scorecard!I79 | J79: =Scorecard!J79 | K79: =Scorecard!K79 | L79: =Scorecard!L79
B80: 6.05 | C80: Customer satisfaction scores / NPS publicly available or referenceable | D80: 1x | E80: =Scorecard!E80 | F80: =Scorecard!F80 | G80: =Scorecard!G80 | H80: =Scorecard!H80 | I80: =Scorecard!I80 | J80: =Scorecard!J80 | K80: =Scorecard!K80 | L80: =Scorecard!L80
B81: 6.06 | C81: Acquisition / ownership stability — no pending M&A risk ★ | D81: 2x | E81: =Scorecard!E81 | F81: =Scorecard!F81 | G81: =Scorecard!G81 | H81: =Scorecard!H81 | I81: =Scorecard!I81 | J81: =Scorecard!J81 | K81: =Scorecard!K81 | L81: =Scorecard!L81
B82: 6.07 | C82: Demonstrated experience in your industry vertical | D82: 1x | E82: =Scorecard!E82 | F82: =Scorecard!F82 | G82: =Scorecard!G82 | H82: =Scorecard!H82 | I82: =Scorecard!I82 | J82: =Scorecard!J82 | K82: =Scorecard!K82 | L82: =Scorecard!L82
B83: 6.08 | C83: Partnership ecosystem (GSI, regional SI partners in your markets) | D83: 1x | E83: =Scorecard!E83 | F83: =Scorecard!F83 | G83: =Scorecard!G83 | H83: =Scorecard!H83 | I83: =Scorecard!I83 | J83: =Scorecard!J83 | K83: =Scorecard!K83 | L83: =Scorecard!L83
