Workbook

Sheet Instructions
B2: AI Tool Comparison Matrix — ChatGPT vs Copilot vs Gemini
B6: ABOUT THIS MATRIX
B8: This matrix provides a structured side-by-side comparison of ChatGPT (OpenAI),
B9: Microsoft Copilot, and Google Gemini for finance use cases — covering performance,
B10: data security, integration, cost, and model quality.
B12: HOW TO USE
B14: Step 1 — Go to the Comparison Matrix sheet to view the full scored comparison.
B15: Step 2 — Review the Best-Fit Guide sheet for a quick decision framework.
B16: Step 3 — Use the My Priorities sheet to weight criteria by your organisation's needs.
B18: SCORING GUIDE
B20: 1 = Poor — significant limitation for finance use
B21: 2 = Below average — notable gaps or constraints
... B32: Free resource · Mirela Dragulescu Consulting

Sheet Comparison Matrix
B2: AI Tool Comparison Matrix — ChatGPT vs Microsoft Copilot vs Google Gemini
B5: WT | C5: CRITERION | D5: ChatGPT (OpenAI) | E5: Microsoft Copilot | F5: Google Gemini | G5: ChatGPT — Notes | H5: Copilot — Notes | I5: Gemini — Notes
B7: 1. FINANCE USE CASE PERFORMANCE
B8: 2x | C8: Variance commentary generation | D8: 4 | E8: 4 | F8: 3 | G8: Strong structured output with R.C.T.F. prompts; reliable for management commentary | H8: Excellent in Excel with Copilot in Excel; commentary in chat mode also strong | I8: Good general output; less finance-specific training; prompt engineering required
B9: 2x | C9: Executive summary drafting | D9: 5 | E9: 4 | F9: 4 | G9: Best-in-class for long-form structured financial narratives with precise constraints | H9: Strong for Word/Outlook integration; slightly less flexible on format instructions | I9: Solid for summaries; strong when connected to Google Workspace documents
B10: 1x | C10: Cash flow narrative writing | D10: 4 | E10: 4 | F10: 3 | G10: Reliable with well-structured prompts; handles bridge narratives well | H10: Good in Teams/Outlook context; requires clear data in prompt | I10: Adequate; tends toward generic language without tight format instructions
B11: 2x | C11: Variance analysis from data tables | D11: 4 | E11: 5 | F11: 3 | G11: Strong; requires data pasted into prompt — no live ERP connection | H11: Excel Copilot can reference live table data directly without copy-paste | I11: Adequate via Gemini Advanced in Sheets; less precise than Copilot in Excel
B12: 1x | C12: Prompt engineering flexibility | D12: 5 | E12: 3 | F12: 4 | G12: Most flexible — accepts complex multi-part instructions reliably | H12: More constrained by Microsoft UI — less flexible for advanced prompting | I12: Good flexibility; Google AI Studio allows advanced configuration
B14: 2. DATA SECURITY &AMP; COMPLIANCE
B15: 2x | C15: GDPR / EU data residency | D15: 3 | E15: 5 | F15: 3 | G15: ChatGPT Enterprise offers EU data residency; free/Plus tiers do not guarantee this | H15: Microsoft 365 Copilot: data stays in EU tenant by default; strong GDPR posture | I15: Google Workspace data residency available for Enterprise; region-specific controls exist
B16: 2x | C16: Training data opt-out | D16: 4 | E16: 5 | F16: 4 | G16: Enterprise tier: data not used for training. Plus/free: opt-out available in settings | H16: Microsoft 365 Copilot: commercial data protection by default — data never trains the model | I16: Workspace Business/Enterprise: data not used for training by default
B17: 1x | C17: Session data retention | D17: 3 | E17: 4 | F17: 3 | G17: Conversations retained; delete manually. Enterprise: configurable retention policies | H17: Data governed by M365 retention policies — aligned to existing IT governance | I17: Conversation history stored; configurable via Workspace Admin for Enterprise
B18: 1x | C18: Audit trail and access logging | D18: 3 | E18: 5 | F18: 3 | G18: Enterprise: admin console with usage monitoring. Limited on free/Plus tiers | H18: Full Microsoft Purview integration — compliance logging, DLP, access controls | I18: Google Admin console logging; Workspace Enterprise has advanced audit capabilities
B19: 2x | C19: Suitability for sensitive financial data | D19: 3 | E19: 5 | F19: 3 | G19: Enterprise tier only. Free/Plus must not be used with price-sensitive or personal data | H19: M365 Copilot with existing M365 E3/E5 licence: safest option for most finance teams | I19: Google Workspace Enterprise only. Requires IT governance sign-off
B21: 3. INTEGRATION &AMP; WORKFLOW
B22: 2x | C22: Microsoft 365 integration (Excel, Word, Outlook, Teams) | D22: 2 | E22: 5 | F22: 2 | G22: No native integration. API available but requires developer setup | H22: Native — Copilot is built into Excel, Word, Outlook, PowerPoint, Teams | I22: Limited. Requires browser switching or API; no native M365 integration
B23: 2x | C23: Google Workspace integration (Sheets, Docs, Gmail) | D23: 2 | E23: 2 | F23: 5 | G23: No native integration with Google Workspace | H23: No native Google Workspace integration | I23: Native — Gemini is built into Google Sheets, Docs, Gmail, Meet
B24: 1x | C24: ERP / finance system connectivity | D24: 2 | E24: 3 | F24: 2 | G24: No direct ERP connection. Data must be pasted into prompt manually | H24: Power Platform connectors available; limited direct ERP integration | I24: Google Cloud connectors available; no direct ERP integration out of the box
B25: 1x | C25: Browser and web research capability | D25: 4 | E25: 4 | F25: 5 | G25: Web browsing available in ChatGPT Plus/Enterprise; reliable for current information | H25: Copilot has strong web search via Bing integration in Teams and browser | I25: Google Search integration gives Gemini the strongest real-time web access
B26: 1x | C26: Mobile accessibility | D26: 4 | E26: 4 | F26: 4 | G26: ChatGPT iOS/Android app: strong mobile experience with voice input | H26: Copilot available in M365 mobile apps; standalone app also available | I26: Gemini app on iOS/Android; integrated into Google app ecosystem
B28: 4. COST &AMP; ACCESSIBILITY
B29: 1x | C29: Free tier availability | D29: 4 | E29: 3 | F29: 4 | G29: ChatGPT free: GPT-3.5 access. Limited but functional for basic tasks | H29: Copilot free tier available via copilot.microsoft.com; limited without M365 | I29: Gemini free tier (1.5 Flash model): strong capability at no cost
B30: 1x | C30: Pricing (per user per month, mid-tier) | D30: 3 | E30: 3 | F30: 4 | G30: ChatGPT Plus: $20/month. Enterprise: custom pricing, typically $30-60/user | H30: M365 Copilot: $30/user/month add-on to M365 E3/E5 licence | I30: Gemini Advanced: $19/month (Google One AI Premium). Business: $22/user/month
B31: 2x | C31: Value for finance teams already in M365 | D31: 2 | E31: 5 | F31: 2 | G31: Adds cost with no native M365 integration — less compelling if team is M365-native | H31: Strong ROI for M365-native finance teams — integrates with existing tools | I31: Adds cost with no M365 integration — not the right choice for M365-first teams
B32: 2x | C32: Value for finance teams in Google Workspace | D32: 2 | E32: 2 | F32: 5 | G32: Adds cost with no Workspace integration — less compelling for Workspace-native teams | H32: Adds cost with no Workspace integration — not the right choice for Workspace teams | I32: Strong ROI for Workspace-native teams — integrates with existing tools
B33: 1x | C33: Licence simplicity | D33: 4 | E33: 3 | F33: 4 | G33: Simple subscription; no dependency on existing productivity licence | H33: Requires existing M365 E3/E5 licence as prerequisite — more complex to procure | I33: Can be purchased independently; also bundled with Google Workspace
B35: 5. MODEL QUALITY &AMP; RELIABILITY
B36: 2x | C36: Instruction following accuracy | D36: 5 | E36: 4 | F36: 4 | G36: GPT-4o: best-in-class for following precise, multi-part instructions in finance prompts | H36: Strong on standard tasks; slightly less reliable on complex nested instructions | I36: Gemini 1.5 Pro: strong instruction following; good on structured output formats
B37: 2x | C37: Hallucination risk for financial content | D37: 3 | E37: 3 | F37: 3 | G37: Hallucinates when asked to retrieve data it does not have. Use only with pasted data | H37: Same risk — all LLMs hallucinate. Microsoft Copilot adds grounding in M365 data | I37: Same risk. Google Search grounding reduces hallucination on factual questions
B38: 1x | C38: Output consistency across sessions | D38: 4 | E38: 4 | F38: 3 | G38: Consistent output quality with well-structured prompts; minor variability in tone | H38: Consistent within M365 apps; less predictable in standalone Copilot chat | I38: More variable output quality; prompt engineering matters more for consistency
B39: 1x | C39: Handling of long financial documents | D39: 5 | E39: 4 | F39: 4 | G39: 128k token context window — handles full board packs and long financial reports | H39: Large context window in M365 Copilot; effective for long Word/Excel documents | I39: 1M token context (Gemini 1.5 Pro) — largest context window of the three tools
B40: 1x | C40: Model updates and improvement rate | D40: 5 | E40: 4 | F40: 4 | G40: OpenAI releases frequent model updates; GPT-4o is current frontier model | H40: Tied to Microsoft release cycle; improvements steady but less frequent | I40: Google DeepMind: rapid Gemini iteration; 1.5 Pro and 2.0 Flash are strong models
C42: TOTAL WEIGHTED SCORE | D42: =IFERROR(SUMPRODUCT((B7:B40="2x")*ISNUMBER(D7:D40)*IF(ISNUMBER(D7:D40),D7:D40,0)*2)+SUMPRODUCT((B7:B40="1x")*ISNUMBER(D7:D40)*IF(ISNUMBER(D7:D40),D7:D40,0)),"") -> 0 | E42: =IFERROR(SUMPRODUCT((B7:B40="2x")*ISNUMBER(E7:E40)*IF(ISNUMBER(E7:E40),E7:E40,0)*2)+SUMPRODUCT((B7:B40="1x")*ISNUMBER(E7:E40)*IF(ISNUMBER(E7:E40),E7:E40,0)),"") -> 0 | F42: =IFERROR(SUMPRODUCT((B7:B40="2x")*ISNUMBER(F7:F40)*IF(ISNUMBER(F7:F40),F7:F40,0)*2)+SUMPRODUCT((B7:B40="1x")*ISNUMBER(F7:F40)*IF(ISNUMBER(F7:F40),F7:F40,0)),"") -> 0
C43: Maximum possible score: 185 (criteria marked 2x count double)

Sheet Best-Fit Guide
B2: Best-Fit Guide — Which Tool for Your Finance Team?
B6: YOUR SITUATION | C6: RECOMMENDED TOOL
B7: You and your team work primarily in Microsoft 365 (Excel, Word, Outlook, Teams) | C7: Microsoft Copilot Integrates natively with your existing tools. No context switching. Data stays in your M365 tenant.
B8: You and your team work primarily in Google Workspace (Sheets, Docs, Gmail, Meet) | C8: Google Gemini Native Workspace integration. Best ROI for Workspace-native teams. Strong real-time search.
B9: You want the most powerful prompt-based finance writing tool with maximum flexibility | C9: ChatGPT (GPT-4o) Best instruction-following for complex, multi-part finance prompts. Ideal for variance commentary and executive narratives.
B10: Data security and GDPR are your primary concern and you are in a regulated industry | C10: Microsoft Copilot (M365 E3/E5) Strongest data governance. Microsoft Purview integration. Commercial data protection by default.
B11: You want to experiment without budget commitment before making a procurement decision | C11: Start with Gemini Free (1.5 Flash) Strongest free tier for finance tasks. Then trial ChatGPT Plus before deciding.
B12: You need a tool that can read and analyse long financial documents (full board packs) | C12: Google Gemini 1.5 Pro Largest context window (1 million tokens). Can process full board packs and lengthy reports in one session.
B13: You want to automate Excel-based finance workflows (variance analysis, data cleaning, formula help) | C13: Microsoft Copilot in Excel The only tool with native Excel integration. Can reference live data in your workbook without copy-paste.
B14: Your organisation has no existing M365 or Workspace licence and you want the simplest procurement path | C14: ChatGPT Plus ($20/month) Simple subscription, no dependencies, strong capability across all finance writing and analysis tasks.
B15: YOU SHOULD NOT USE ANY AI TOOL (yet) IF: | C15: Review the AI Governance Checklist for Finance first
B16: Your financial data contains personal employee data, price-sensitive information, or audit workpapers | C16: None of the above tools are appropriate for this data without Enterprise-grade controls and explicit IT/Legal approval.
B18: Note: Scores and recommendations reflect the tool landscape as of June 2026. Pricing, features, and security terms change frequently — verify before procurement.

Sheet My Priorities
B2: My Priorities — Weighted Score by Your Organisation's Needs
B6: Rate each dimension 1–5 by importance to your organisation. The weighted score shows which tool best matches your specific priorities.
B8: DIMENSION | C8: Your Priority (1–5) | D8: ChatGPT Sect. Score | E8: Copilot Sect. Score | F8: Gemini Sect. Score
B9: 1. Finance Use Case Performance | C9: 5 | D9: =IFERROR(SUMPRODUCT(('Comparison Matrix'!B8:B12="2x")*ISNUMBER('Comparison Matrix'!D8:'Comparison Matrix'!D12)*IF(ISNUMBER('Comparison Matrix'!D8:'Comparison Matrix'!D12),'Comparison Matrix'!D8:'Comparison Matrix'!D12,0)*2)+SUMPRODUCT(('Comparison Matrix'!B8:B12="1x")*ISNUMBER('Comparison Matrix'!D8:'Comparison Matrix'!D12)*IF(ISNUMBER('Comparison Matrix'!D8:'Comparison Matrix'!D12),'Comparison Matrix'!D8:'Comparison Matrix'!D12,0)),"-") -> 35 | E9: =IFERROR(SUMPRODUCT(('Comparison Matrix'!B8:B12="2x")*ISNUMBER('Comparison Matrix'!E8:'Comparison Matrix'!E12)*IF(ISNUMBER('Comparison Matrix'!E8:'Comparison Matrix'!E12),'Comparison Matrix'!E8:'Comparison Matrix'!E12,0)*2)+SUMPRODUCT(('Comparison Matrix'!B8:B12="1x")*ISNUMBER('Comparison Matrix'!E8:'Comparison Matrix'!E12)*IF(ISNUMBER('Comparison Matrix'!E8:'Comparison Matrix'!E12),'Comparison Matrix'!E8:'Comparison Matrix'!E12,0)),"-") -> 33 | F9: =IFERROR(SUMPRODUCT(('Comparison Matrix'!B8:B12="2x")*ISNUMBER('Comparison Matrix'!F8:'Comparison Matrix'!F12)*IF(ISNUMBER('Comparison Matrix'!F8:'Comparison Matrix'!F12),'Comparison Matrix'!F8:'Comparison Matrix'!F12,0)*2)+SUMPRODUCT(('Comparison Matrix'!B8:B12="1x")*ISNUMBER('Comparison Matrix'!F8:'Comparison Matrix'!F12)*IF(ISNUMBER('Comparison Matrix'!F8:'Comparison Matrix'!F12),'Comparison Matrix'!F8:'Comparison Matrix'!F12,0)),"-") -> 27
B10: 2. Data Security & Compliance | C10: 4 | D10: =IFERROR(SUMPRODUCT(('Comparison Matrix'!B15:B19="2x")*ISNUMBER('Comparison Matrix'!D15:'Comparison Matrix'!D19)*IF(ISNUMBER('Comparison Matrix'!D15:'Comparison Matrix'!D19),'Comparison Matrix'!D15:'Comparison Matrix'!D19,0)*2)+SUMPRODUCT(('Comparison Matrix'!B15:B19="1x")*ISNUMBER('Comparison Matrix'!D15:'Comparison Matrix'!D19)*IF(ISNUMBER('Comparison Matrix'!D15:'Comparison Matrix'!D19),'Comparison Matrix'!D15:'Comparison Matrix'!D19,0)),"-") -> 0 | E10: =IFERROR(SUMPRODUCT(('Comparison Matrix'!B15:B19="2x")*ISNUMBER('Comparison Matrix'!E15:'Comparison Matrix'!E19)*IF(ISNUMBER('Comparison Matrix'!E15:'Comparison Matrix'!E19),'Comparison Matrix'!E15:'Comparison Matrix'!E19,0)*2)+SUMPRODUCT(('Comparison Matrix'!B15:B19="1x")*ISNUMBER('Comparison Matrix'!E15:'Comparison Matrix'!E19)*IF(ISNUMBER('Comparison Matrix'!E15:'Comparison Matrix'!E19),'Comparison Matrix'!E15:'Comparison Matrix'!E19,0)),"-") -> 0 | F10: =IFERROR(SUMPRODUCT(('Comparison Matrix'!B15:B19="2x")*ISNUMBER('Comparison Matrix'!F15:'Comparison Matrix'!F19)*IF(ISNUMBER('Comparison Matrix'!F15:'Comparison Matrix'!F19),'Comparison Matrix'!F15:'Comparison Matrix'!F19,0)*2)+SUMPRODUCT(('Comparison Matrix'!B15:B19="1x")*ISNUMBER('Comparison Matrix'!F15:'Comparison Matrix'!F19)*IF(ISNUMBER('Comparison Matrix'!F15:'Comparison Matrix'!F19),'Comparison Matrix'!F15:'Comparison Matrix'!F19,0)),"-") -> 0
B11: 3. Integration & Workflow | C11: 4 | D11: =IFERROR(SUMPRODUCT(('Comparison Matrix'!B22:B26="2x")*ISNUMBER('Comparison Matrix'!D22:'Comparison Matrix'!D26)*IF(ISNUMBER('Comparison Matrix'!D22:'Comparison Matrix'!D26),'Comparison Matrix'!D22:'Comparison Matrix'!D26,0)*2)+SUMPRODUCT(('Comparison Matrix'!B22:B26="1x")*ISNUMBER('Comparison Matrix'!D22:'Comparison Matrix'!D26)*IF(ISNUMBER('Comparison Matrix'!D22:'Comparison Matrix'!D26),'Comparison Matrix'!D22:'Comparison Matrix'!D26,0)),"-") -> 0 | E11: =IFERROR(SUMPRODUCT(('Comparison Matrix'!B22:B26="2x")*ISNUMBER('Comparison Matrix'!E22:'Comparison Matrix'!E26)*IF(ISNUMBER('Comparison Matrix'!E22:'Comparison Matrix'!E26),'Comparison Matrix'!E22:'Comparison Matrix'!E26,0)*2)+SUMPRODUCT(('Comparison Matrix'!B22:B26="1x")*ISNUMBER('Comparison Matrix'!E22:'Comparison Matrix'!E26)*IF(ISNUMBER('Comparison Matrix'!E22:'Comparison Matrix'!E26),'Comparison Matrix'!E22:'Comparison Matrix'!E26,0)),"-") -> 0 | F11: =IFERROR(SUMPRODUCT(('Comparison Matrix'!B22:B26="2x")*ISNUMBER('Comparison Matrix'!F22:'Comparison Matrix'!F26)*IF(ISNUMBER('Comparison Matrix'!F22:'Comparison Matrix'!F26),'Comparison Matrix'!F22:'Comparison Matrix'!F26,0)*2)+SUMPRODUCT(('Comparison Matrix'!B22:B26="1x")*ISNUMBER('Comparison Matrix'!F22:'Comparison Matrix'!F26)*IF(ISNUMBER('Comparison Matrix'!F22:'Comparison Matrix'!F26),'Comparison Matrix'!F22:'Comparison Matrix'!F26,0)),"-") -> 0
B12: 4. Cost & Accessibility | C12: 3 | D12: =IFERROR(SUMPRODUCT(('Comparison Matrix'!B29:B33="2x")*ISNUMBER('Comparison Matrix'!D29:'Comparison Matrix'!D33)*IF(ISNUMBER('Comparison Matrix'!D29:'Comparison Matrix'!D33),'Comparison Matrix'!D29:'Comparison Matrix'!D33,0)*2)+SUMPRODUCT(('Comparison Matrix'!B29:B33="1x")*ISNUMBER('Comparison Matrix'!D29:'Comparison Matrix'!D33)*IF(ISNUMBER('Comparison Matrix'!D29:'Comparison Matrix'!D33),'Comparison Matrix'!D29:'Comparison Matrix'!D33,0)),"-") -> 0 | E12: =IFERROR(SUMPRODUCT(('Comparison Matrix'!B29:B33="2x")*ISNUMBER('Comparison Matrix'!E29:'Comparison Matrix'!E33)*IF(ISNUMBER('Comparison Matrix'!E29:'Comparison Matrix'!E33),'Comparison Matrix'!E29:'Comparison Matrix'!E33,0)*2)+SUMPRODUCT(('Comparison Matrix'!B29:B33="1x")*ISNUMBER('Comparison Matrix'!E29:'Comparison Matrix'!E33)*IF(ISNUMBER('Comparison Matrix'!E29:'Comparison Matrix'!E33),'Comparison Matrix'!E29:'Comparison Matrix'!E33,0)),"-") -> 0 | F12: =IFERROR(SUMPRODUCT(('Comparison Matrix'!B29:B33="2x")*ISNUMBER('Comparison Matrix'!F29:'Comparison Matrix'!F33)*IF(ISNUMBER('Comparison Matrix'!F29:'Comparison Matrix'!F33),'Comparison Matrix'!F29:'Comparison Matrix'!F33,0)*2)+SUMPRODUCT(('Comparison Matrix'!B29:B33="1x")*ISNUMBER('Comparison Matrix'!F29:'Comparison Matrix'!F33)*IF(ISNUMBER('Comparison Matrix'!F29:'Comparison Matrix'!F33),'Comparison Matrix'!F29:'Comparison Matrix'!F33,0)),"-") -> 0
B13: 5. Model Quality & Reliability | C13: 4 | D13: =IFERROR(SUMPRODUCT(('Comparison Matrix'!B36:B40="2x")*ISNUMBER('Comparison Matrix'!D36:'Comparison Matrix'!D40)*IF(ISNUMBER('Comparison Matrix'!D36:'Comparison Matrix'!D40),'Comparison Matrix'!D36:'Comparison Matrix'!D40,0)*2)+SUMPRODUCT(('Comparison Matrix'!B36:B40="1x")*ISNUMBER('Comparison Matrix'!D36:'Comparison Matrix'!D40)*IF(ISNUMBER('Comparison Matrix'!D36:'Comparison Matrix'!D40),'Comparison Matrix'!D36:'Comparison Matrix'!D40,0)),"-") -> 0 | E13: =IFERROR(SUMPRODUCT(('Comparison Matrix'!B36:B40="2x")*ISNUMBER('Comparison Matrix'!E36:'Comparison Matrix'!E40)*IF(ISNUMBER('Comparison Matrix'!E36:'Comparison Matrix'!E40),'Comparison Matrix'!E36:'Comparison Matrix'!E40,0)*2)+SUMPRODUCT(('Comparison Matrix'!B36:B40="1x")*ISNUMBER('Comparison Matrix'!E36:'Comparison Matrix'!E40)*IF(ISNUMBER('Comparison Matrix'!E36:'Comparison Matrix'!E40),'Comparison Matrix'!E36:'Comparison Matrix'!E40,0)),"-") -> 0 | F13: =IFERROR(SUMPRODUCT(('Comparison Matrix'!B36:B40="2x")*ISNUMBER('Comparison Matrix'!F36:'Comparison Matrix'!F40)*IF(ISNUMBER('Comparison Matrix'!F36:'Comparison Matrix'!F40),'Comparison Matrix'!F36:'Comparison Matrix'!F40,0)*2)+SUMPRODUCT(('Comparison Matrix'!B36:B40="1x")*ISNUMBER('Comparison Matrix'!F36:'Comparison Matrix'!F40)*IF(ISNUMBER('Comparison Matrix'!F36:'Comparison Matrix'!F40),'Comparison Matrix'!F36:'Comparison Matrix'!F40,0)),"-") -> 0
B14: PRIORITY-WEIGHTED TOTAL | D14: =IFERROR(C9*D9+C10*D10+C11*D11+C12*D12+C13*D13,-1) -> 175 | E14: =IFERROR(C9*E9+C10*E10+C11*E11+C12*E12+C13*E13,-1) -> 165 | F14: =IFERROR(C9*F9+C10*F10+C11*F11+C12*F12+C13*F13,-1) -> 135
B16: Adjust the Priority scores (blue cells) to reflect your organisation's needs. The weighted total recalculates automatically.
