Workbook

Sheet Instructions
B2: T&E Vendor Evaluation Scorecard
B6: Free resource · Mirela Dragulescu Consulting · mdconsulting.netlify.app
B8: ABOUT THIS SCORECARD
B10: This scorecard helps finance and procurement teams evaluate T&E platform vendors
B11: consistently and objectively during the RFP and selection process.
B13: It covers four evaluation dimensions:
B14: 1. Functionality & Features
B15: 2. Implementation & Support
B16: 3. Commercial Terms
B17: 4. European Compliance
B19: This free version scores up to 3 vendors across 28 criteria.
B20: The premium version covers 60 criteria across 6 dimensions and supports
... B38: Criteria marked with ★ are weighted 2x in the total score.

Sheet Scorecard
B2: T&E Vendor Evaluation Scorecard
C5: Criterion | D5: Wt | E5: ► Enter vendor name | F5: ► Enter vendor name | G5: ► Enter vendor name | H5: Notes / Evidence
B7: # | C7: CRITERION | D7: WT | E7: SCORE (0–5) | F7: SCORE (0–5) | G7: SCORE (0–5) | H7: NOTES
B8: 1. FUNCTIONALITY & FEATURES
B9: 1.1 | C9: Expense submission via mobile app (iOS & Android) ★ | D9: 2x
B10: 1.2 | C10: Receipt capture via OCR / photo scan ★ | D10: 2x
B11: 1.3 | C11: Multi-currency support and automatic exchange rate updates ★ | D11: 2x
B12: 1.4 | C12: Automated policy checking and out-of-policy flagging ★ | D12: 2x
B13: 1.5 | C13: Configurable approval workflows (multi-level, by amount, by entity) ★ | D13: 2x
B14: 1.6 | C14: Corporate card integration and automatic transaction import | D14: 1x
B15: 1.7 | C15: Per diem and mileage calculation engine | D15: 1x
B16: 1.8 | C16: Offline mode for expense submission without connectivity | D16: 1x
B17: 1.9 | C17: Reporting and analytics dashboard (spend by category, entity, user) | D17: 1x
B18: 1.10 | C18: Bulk approval and finance review workflows | D18: 1x
B20: 2. IMPLEMENTATION & SUPPORT
B21: 2.1 | C21: Dedicated implementation consultant assigned to the project ★ | D21: 2x
B22: 2.2 | C22: Structured implementation methodology with defined phases ★ | D22: 2x
B23: 2.3 | C23: Data migration support (historical expenses, cost centres, users) ★ | D23: 2x
B24: 2.4 | C24: Training materials available in all required languages ★ | D24: 2x
B25: 2.5 | C25: Sandbox / test environment provided during implementation | D25: 1x
B26: 2.6 | C26: Post-go-live hypercare period (minimum 4 weeks) | D26: 1x
B27: 2.7 | C27: SLA for critical incident response (target: < 4 hours) | D27: 1x
B29: 3. COMMERCIAL TERMS
B30: 3.1 | C30: Pricing model is transparent and per-user (not per-transaction) ★ | D30: 2x
B31: 3.2 | C31: Contract terms allow for entity / country additions without renegotiation ★ | D31: 2x
B32: 3.3 | C32: Exit clause — data export and transition support included ★ | D32: 2x
B33: 3.4 | C33: No hidden implementation or setup fees beyond quoted price | D33: 1x
B34: 3.5 | C34: References available from comparable European programmes | D34: 1x
B35: 3.6 | C35: Vendor financial stability — established > 5 years, funded, or profitable | D35: 1x
B37: 4. EUROPEAN COMPLIANCE
B38: 4.1 | C38: GDPR compliance — data processed within EU / EEA by default ★ | D38: 2x
B39: 4.2 | C39: German receipt and expense documentation requirements (GoBD) ★ | D39: 2x
B40: 4.3 | C40: French per diem rules (URSSAF rates, domestic vs international) ★ | D40: 2x
B41: 4.4 | C41: Spanish IVA / VAT reporting and deductibility classification ★ | D41: 2x
B42: 4.5 | C42: Dutch representation expense and 80% rule support | D42: 1x
B43: 4.6 | C43: Works council / CSE information requirements for France | D43: 1x
B44: 4.7 | C44: Country-specific audit trail and archiving requirements | D44: 1x
B45: 4.8 | C45: VAT reclaim support for business travel expenses (EU-wide) | D45: 1x
C47: TOTAL WEIGHTED SCORE | E47: =IFERROR(SUMPRODUCT((D8:D45="2x")*ISNUMBER(E8:E45)*IF(ISNUMBER(E8:E45),E8:E45,0)*2)+SUMPRODUCT((D8:D45="1x")*ISNUMBER(E8:E45)*IF(ISNUMBER(E8:E45),E8:E45,0),"") | F47: =IFERROR(SUMPRODUCT((D8:D45="2x")*ISNUMBER(F8:F45)*IF(ISNUMBER(F8:F45),F8:F45,0)*2)+SUMPRODUCT((D8:D45="1x")*ISNUMBER(F8:F45)*IF(ISNUMBER(F8:F45),F8:F45,0),"") | G47: =IFERROR(SUMPRODUCT((D8:D45="2x")*ISNUMBER(G8:G45)*IF(ISNUMBER(G8:G45),G8:G45,0)*2)+SUMPRODUCT((D8:D45="1x")*ISNUMBER(G8:G45)*IF(ISNUMBER(G8:G45),G8:G45,0),"")
C48: Maximum possible score: 235 (weighted criteria count 2x)

Sheet Summary
B2: Vendor Evaluation — Summary
B5: VENDOR | C5: =IF(Scorecard!E5="► Enter vendor name","Vendor 1",Scorecard!E5) | D5: =IF(Scorecard!F5="► Enter vendor name","Vendor 2",Scorecard!F5) | E5: =IF(Scorecard!G5="► Enter vendor name","Vendor 3",Scorecard!G5)
B7: TOTAL WEIGHTED SCORE | C7: =Scorecard!E47 | D7: =Scorecard!F47 | E7: =Scorecard!G47
B8: Maximum possible score: 235 · Weighted criteria (★) count double
B10: Score as % of maximum | C10: =IFERROR(C7/235,"-") | D10: =IFERROR(D7/235,"-") | E10: =IFERROR(E7/235,"-")
B12: Rank | C12: =IFERROR(RANK(C7,C7:E7,0),"-") | D12: =IFERROR(RANK(D7,C7:E7,0),"-") | E12: =IFERROR(RANK(E7,C7:E7,0),"-")
B14: SCORE BY SECTION
B15: 1. Functionality & Features | C15: =IFERROR(SUMPRODUCT((Scorecard!D9:D18="2x")*ISNUMBER(Scorecard!E9:Scorecard!E18)*IF(ISNUMBER(Scorecard!E9:Scorecard!E18),Scorecard!E9:Scorecard!E18,0)*2)+SUMPRODUCT((Scorecard!D9:D18="1x")*ISNUMBER(Scorecard!E9:Scorecard!E18)*IF(ISNUMBER(Scorecard!E9:Scorecard!E18),Scorecard!E9:Scorecard!E18,0))&" / 75","-") | D15: =IFERROR(SUMPRODUCT((Scorecard!D9:D18="2x")*ISNUMBER(Scorecard!F9:Scorecard!F18)*IF(ISNUMBER(Scorecard!F9:Scorecard!F18),Scorecard!F9:Scorecard!F18,0)*2)+SUMPRODUCT((Scorecard!D9:D18="1x")*ISNUMBER(Scorecard!F9:Scorecard!F18)*IF(ISNUMBER(Scorecard!F9:Scorecard!F18),Scorecard!F9:Scorecard!F18,0))&" / 75","-") | E15: =IFERROR(SUMPRODUCT((Scorecard!D9:D18="2x")*ISNUMBER(Scorecard!G9:Scorecard!G18)*IF(ISNUMBER(Scorecard!G9:Scorecard!G18),Scorecard!G9:Scorecard!G18,0)*2)+SUMPRODUCT((Scorecard!D9:D18="1x")*ISNUMBER(Scorecard!G9:Scorecard!G18)*IF(ISNUMBER(Scorecard!G9:Scorecard!G18),Scorecard!G9:Scorecard!G18,0))&" / 75","-")
B16: 2. Implementation & Support | C16: =IFERROR(SUMPRODUCT((Scorecard!D21:D27="2x")*ISNUMBER(Scorecard!E21:Scorecard!E27)*IF(ISNUMBER(Scorecard!E21:Scorecard!E27),Scorecard!E21:Scorecard!E27,0)*2)+SUMPRODUCT((Scorecard!D21:D27="1x")*ISNUMBER(Scorecard!E21:Scorecard!E27)*IF(ISNUMBER(Scorecard!E21:Scorecard!E27),Scorecard!E21:Scorecard!E27,0))&" / 55","-") | D16: =IFERROR(SUMPRODUCT((Scorecard!D21:D27="2x")*ISNUMBER(Scorecard!F21:Scorecard!F27)*IF(ISNUMBER(Scorecard!F21:Scorecard!F27),Scorecard!F21:Scorecard!F27,0)*2)+SUMPRODUCT((Scorecard!D21:D27="1x")*ISNUMBER(Scorecard!F21:Scorecard!F27)*IF(ISNUMBER(Scorecard!F21:Scorecard!F27),Scorecard!F21:Scorecard!F27,0))&" / 55","-") | E16: =IFERROR(SUMPRODUCT((Scorecard!D21:D27="2x")*ISNUMBER(Scorecard!G21:Scorecard!G27)*IF(ISNUMBER(Scorecard!G21:Scorecard!G27),Scorecard!G21:Scorecard!G27,0)*2)+SUMPRODUCT((Scorecard!D21:D27="1x")*ISNUMBER(Scorecard!G21:Scorecard!G27)*IF(ISNUMBER(Scorecard!G21:Scorecard!G27),Scorecard!G21:Scorecard!G27,0))&" / 55","-")
B17: 3. Commercial Terms | C17: =IFERROR(SUMPRODUCT((Scorecard!D30:D35="2x")*ISNUMBER(Scorecard!E30:Scorecard!E35)*IF(ISNUMBER(Scorecard!E30:Scorecard!E35),Scorecard!E30:Scorecard!E35,0)*2)+SUMPRODUCT((Scorecard!D30:D35="1x")*ISNUMBER(Scorecard!E30:Scorecard!E35)*IF(ISNUMBER(Scorecard!E30:Scorecard!E35),Scorecard!E30:Scorecard!E35,0))&" / 45","-") | D17: =IFERROR(SUMPRODUCT((Scorecard!D30:D35="2x")*ISNUMBER(Scorecard!F30:Scorecard!F35)*IF(ISNUMBER(Scorecard!F30:Scorecard!F35),Scorecard!F30:Scorecard!F35,0)*2)+SUMPRODUCT((Scorecard!D30:D35="1x")*ISNUMBER(Scorecard!F30:Scorecard!F35)*IF(ISNUMBER(Scorecard!F30:Scorecard!F35),Scorecard!F30:Scorecard!F35,0))&" / 45","-") | E17: =IFERROR(SUMPRODUCT((Scorecard!D30:D35="2x")*ISNUMBER(Scorecard!G30:Scorecard!G35)*IF(ISNUMBER(Scorecard!G30:Scorecard!G35),Scorecard!G30:Scorecard!G35,0)*2)+SUMPRODUCT((Scorecard!D30:D35="1x")*ISNUMBER(Scorecard!G30:Scorecard!G35)*IF(ISNUMBER(Scorecard!G30:Scorecard!G35),Scorecard!G30:Scorecard!G35,0))&" / 45","-")
B18: 4. European Compliance | C18: =IFERROR(SUMPRODUCT((Scorecard!D38:D45="2x")*ISNUMBER(Scorecard!E38:Scorecard!E45)*IF(ISNUMBER(Scorecard!E38:Scorecard!E45),Scorecard!E38:Scorecard!E45,0)*2)+SUMPRODUCT((Scorecard!D38:D45="1x")*ISNUMBER(Scorecard!E38:Scorecard!E45)*IF(ISNUMBER(Scorecard!E38:Scorecard!E45),Scorecard!E38:Scorecard!E45,0))&" / 60","-") | D18: =IFERROR(SUMPRODUCT((Scorecard!D38:D45="2x")*ISNUMBER(Scorecard!F38:Scorecard!F45)*IF(ISNUMBER(Scorecard!F38:Scorecard!F45),Scorecard!F38:Scorecard!F45,0)*2)+SUMPRODUCT((Scorecard!D38:D45="1x")*ISNUMBER(Scorecard!F38:Scorecard!F45)*IF(ISNUMBER(Scorecard!F38:Scorecard!F45),Scorecard!F38:Scorecard!F45,0))&" / 60","-") | E18: =IFERROR(SUMPRODUCT((Scorecard!D38:D45="2x")*ISNUMBER(Scorecard!G38:Scorecard!G45)*IF(ISNUMBER(Scorecard!G38:Scorecard!G45),Scorecard!G38:Scorecard!G45,0)*2)+SUMPRODUCT((Scorecard!D38:D45="1x")*ISNUMBER(Scorecard!G38:Scorecard!G45)*IF(ISNUMBER(Scorecard!G38:Scorecard!G45),Scorecard!G38:Scorecard!G45,0))&" / 60","-")
B20: RECOMMENDATION
B21: Add your recommendation and rationale here after completing the scoring.
B23: Free version: 28 criteria, 4 dimensions, 3 vendors. Premium version: 60 criteria, 6 dimensions, unlimited vendors, weighted scoring dashboard. mdconsulting.netlify.app/resources
